{"type": "Feature", "id": 12522411, "geometry": {"type": "Point", "coordinates": [-158.028275, 21.48666]}, "properties": {"woe:id": 12522411, "woe:parent_id": 2518944, "woe:name": "Wheeler Army Air Field", "woe:placetype": 14, "woe:placetype_name": "Airport", "woe:lang": "ENG", "iso:country": "US", "meta:provider": ["geoplanet:7.3.2", "geoplanet:7.4.0", "geoplanet:7.4.1", "geoplanet:7.5.1", "geoplanet:7.5.2", "geoplanet:7.6.0", "geoplanet:7.8.1", "geoplanet:7.9.0", "geoplanet:7.10.0", "geoplanet:8.0.0", "woeplanet:8.0.0"], "meta:indexed": "2020-08-20T21:58:46.971898", "woe:alias_ENG_V": ["HHI Airport", "Wheeler AFB", "Wheeler AAF", "Wheeler Air Force Base", "Wheeler Army Airfield", "Wheeler Army Field", "HHI"], "meta:updated": "2020-10-14T11:44:09.222669", "woe:hierarchy": {"continent": 24865672, "country": 23424977, "town": 0, "planet": 1, "county": 12588030, "suburb": 0, "state": 2347570, "region": 0, "localadmin": 0}, "woe:timezone_id": 28350949, "woe:hash": "87zd5zx2f79x", "woe:centroid": [-158.028275, 21.48666], "geom:latitude": 21.48666, "geom:longitude": -158.028275, "geom:hash": "87zd5zx2f79x", "woe:latitude": 21.48666, "geom:centroid": [-158.028275, 21.48666], "woe:longitude": -158.028275, "woe:repo": "woeplanet-airport-us", "geom:area": 0.0, "woe:scale": 19}}