{"type": "Feature", "id": 56049498, "geometry": {"type": "Point", "coordinates": [-97.312599, 36.801048]}, "properties": {"woe:id": 56049498, "woe:parent_id": 2365095, "woe:name": "Earl Henry Airport", "woe:placetype": 14, "woe:placetype_name": "Airport", "woe:lang": "ENG", "iso:country": "US", "meta:provider": ["geoplanet:7.3.1", "geoplanet:7.3.2", "geoplanet:7.4.0", "geoplanet:7.4.1", "geoplanet:7.5.1", "geoplanet:7.5.2", "geoplanet:7.6.0", "geoplanet:7.8.1", "geoplanet:7.9.0", "geoplanet:7.10.0", "geoplanet:8.0.0", "woeplanet:8.0.0"], "meta:indexed": "2020-08-20T20:15:35.942256", "woe:alias_ENG_V": ["6ok6"], "meta:updated": "2020-10-14T11:44:07.621744", "woe:hierarchy": {"continent": 24865672, "country": 23424977, "town": 0, "planet": 1, "county": 12589650, "suburb": 0, "state": 2347595, "region": 0, "localadmin": 0}, "woe:timezone_id": 56043661, "woe:hash": "9ydc3e7jshdf", "woe:centroid": [-97.312599, 36.801048], "geom:latitude": 36.801048, "geom:longitude": -97.312599, "geom:hash": "9ydc3e7jshdf", "woe:latitude": 36.801048, "geom:centroid": [-97.312599, 36.801048], "woe:longitude": -97.312599, "woe:repo": "woeplanet-airport-us", "geom:area": 0.0, "woe:scale": 19}}