{"type": "Feature", "id": 29388291, "geometry": {"type": "Point", "coordinates": [-86.805099, 40.38937]}, "properties": {"woe:id": 29388291, "woe:parent_id": 2389886, "woe:name": "Halsmer Airport", "woe:placetype": 14, "woe:placetype_name": "Airport", "woe:lang": "ENG", "iso:country": "US", "meta:provider": ["geoplanet:7.3.1", "geoplanet:7.3.2", "geoplanet:7.4.0", "geoplanet:7.4.1", "geoplanet:7.5.1", "geoplanet:7.5.2", "geoplanet:7.6.0", "geoplanet:7.8.1", "geoplanet:7.9.0", "geoplanet:7.10.0", "geoplanet:8.0.0", "woeplanet:8.0.0"], "meta:indexed": "2020-08-20T20:15:32.977563", "meta:updated": "2020-10-14T11:44:06.965880", "woe:hierarchy": {"continent": 24865672, "country": 23424977, "town": 0, "planet": 1, "county": 12588258, "suburb": 0, "state": 2347573, "region": 0, "localadmin": 0}, "woe:timezone_id": 56043656, "woe:hash": "dp4mb8wmns6b", "woe:centroid": [-86.805099, 40.38937], "geom:latitude": 40.38937, "geom:longitude": -86.805099, "geom:hash": "dp4mb8wmns6b", "woe:latitude": 40.38937, "geom:centroid": [-86.805099, 40.38937], "woe:longitude": -86.805099, "woe:repo": "woeplanet-airport-us", "geom:area": 0.0, "woe:scale": 19}}