{"type": "Feature", "id": 29388346, "geometry": {"type": "Point", "coordinates": [-85.099777, 37.006882]}, "properties": {"woe:id": 29388346, "woe:parent_id": 2428547, "woe:name": "Russell County Airport", "woe:placetype": 14, "woe:placetype_name": "Airport", "woe:lang": "ENG", "iso:country": "US", "meta:provider": ["geoplanet:7.3.1", "geoplanet:7.3.2", "geoplanet:7.4.0", "geoplanet:7.4.1", "geoplanet:7.5.1", "geoplanet:7.5.2", "geoplanet:7.6.0", "geoplanet:7.8.1", "geoplanet:7.9.0", "geoplanet:7.10.0", "geoplanet:8.0.0", "woeplanet:8.0.0"], "meta:indexed": "2020-08-20T20:15:35.792078", "woe:alias_ENG_V": ["K24"], "meta:updated": "2020-10-14T11:44:06.939688", "woe:hierarchy": {"continent": 24865672, "country": 23424977, "town": 0, "planet": 1, "county": 12588579, "suburb": 0, "state": 2347576, "region": 0, "localadmin": 0}, "woe:timezone_id": 56043647, "woe:hash": "dne6x8bhxqz1", "woe:centroid": [-85.099777, 37.006882], "geom:latitude": 37.006882, "geom:longitude": -85.099777, "geom:hash": "dne6x8bhxqz1", "woe:latitude": 37.006882, "geom:centroid": [-85.099777, 37.006882], "woe:longitude": -85.099777, "woe:repo": "woeplanet-airport-us", "geom:area": 0.0, "woe:scale": 19}}