{"type": "Feature", "id": 12521904, "properties": {"woe:id": 12521904, "woe:parent_id": 2521863, "woe:name": "Sonoma County Airport", "woe:placetype": 14, "woe:placetype_name": "Airport", "woe:lang": "ENG", "iso:country": "US", "meta:provider": ["geoplanet:7.3.1", "geoplanet:7.3.2", "geoplanet:7.4.0", "geoplanet:7.4.1", "geoplanet:7.5.1", "geoplanet:7.5.2", "geoplanet:7.6.0", "geoplanet:7.8.1", "geoplanet:7.9.0", "geoplanet:7.10.0", "geoplanet:8.0.0", "woeplanet:8.0.0"], "meta:indexed": "2020-08-20T20:15:34.961412", "woe:alias_ENG_V": ["Charles M Schulz Sonoma Co Airport", "Sonoma Airport", "STS", "Charles M Schulz Sonoma County Airport", "STS Airport", "Charles M. Schulz - Sonoma County Airport"], "meta:updated": "2020-08-22T02:54:59.364409", "woe:hierarchy": {"continent": 24865672, "country": 23424977, "town": 0, "planet": 1, "county": 12587718, "suburb": 0, "state": 2347563, "region": 0, "localadmin": 0}, "woe:timezone_id": 56043663, "woe:hash": "9qbejd8nsqb3", "woe:centroid": [-122.804993, 38.510979], "geom:latitude": 38.510979, "geom:longitude": -122.804993, "geom:hash": "9qbejd8nsqb3", "woe:latitude": 38.510979, "geom:centroid": [-122.804993, 38.510979], "woe:longitude": -122.804993, "woe:repo": "woeplanet-airport-us"}, "geometry": {"coordinates": [-122.804993, 38.510979], "type": "Point"}}