{"type": "Feature", "id": 29388266, "properties": {"woe:id": 29388266, "woe:parent_id": 2379195, "woe:name": "Howard Nixon Memorial Airport", "woe:placetype": 14, "woe:placetype_name": "Airport", "woe:lang": "ENG", "iso:country": "US", "meta:provider": ["geoplanet:7.3.1", "geoplanet:7.3.2", "geoplanet:7.4.0", "geoplanet:7.4.1", "geoplanet:7.5.1", "geoplanet:7.5.2", "geoplanet:7.6.0", "geoplanet:7.8.1", "geoplanet:7.9.0", "geoplanet:7.10.0", "geoplanet:8.0.0", "woeplanet:8.0.0"], "meta:indexed": "2020-08-20T20:15:35.747170", "woe:alias_ENG_V": ["50g"], "meta:updated": "2020-08-22T02:54:59.922699", "woe:hierarchy": {"continent": 24865672, "country": 23424977, "town": 0, "planet": 1, "county": 12588786, "suburb": 0, "state": 2347581, "region": 0, "localadmin": 0}, "woe:timezone_id": 56043658, "woe:hash": "dpsjttghfb4y", "woe:centroid": [-84.129059, 43.186699], "geom:latitude": 43.186699, "geom:longitude": -84.129059, "geom:hash": "dpsjttghfb4y", "woe:latitude": 43.186699, "geom:centroid": [-84.129059, 43.186699], "woe:longitude": -84.129059, "woe:repo": "woeplanet-airport-us"}, "geometry": {"coordinates": [-84.129059, 43.186699], "type": "Point"}}