{"type": "Feature", "id": 29388521, "geometry": {"type": "Point", "coordinates": [-79.522499, 35.877869]}, "properties": {"woe:id": 29388521, "woe:parent_id": 2473854, "woe:name": "Hinshaw Airport", "woe:placetype": 14, "woe:placetype_name": "Airport", "woe:lang": "ENG", "iso:country": "US", "meta:provider": ["geoplanet:7.3.1", "geoplanet:7.3.2", "geoplanet:7.4.0", "geoplanet:7.4.1", "geoplanet:7.5.1", "geoplanet:7.5.2", "geoplanet:7.6.0", "geoplanet:7.8.1", "geoplanet:7.9.0", "geoplanet:7.10.0", "geoplanet:8.0.0", "woeplanet:8.0.0"], "meta:indexed": "2020-08-20T20:15:33.023207", "woe:alias_ENG_V": ["N61"], "meta:updated": "2020-10-14T11:44:06.796116", "woe:hierarchy": {"continent": 24865672, "country": 23424977, "town": 0, "planet": 1, "county": 12589374, "suburb": 0, "state": 2347592, "region": 0, "localadmin": 0}, "woe:timezone_id": 56043648, "woe:hash": "dnrkn7m7xrwc", "woe:centroid": [-79.522499, 35.877869], "geom:latitude": 35.877869, "geom:longitude": -79.522499, "geom:hash": "dnrkn7m7xrwc", "woe:latitude": 35.877869, "geom:centroid": [-79.522499, 35.877869], "woe:longitude": -79.522499, "woe:repo": "woeplanet-airport-us", "geom:area": 0.0, "woe:scale": 19}}