{"type": "Feature", "id": 12520145, "geometry": {"type": "Point", "coordinates": [-75.992729, 40.988461]}, "properties": {"woe:id": 12520145, "woe:parent_id": 2419310, "woe:name": "Hazleton Municipal Airport", "woe:placetype": 14, "woe:placetype_name": "Airport", "woe:lang": "ENG", "iso:country": "US", "meta:provider": ["geoplanet:7.3.1", "geoplanet:7.3.2", "geoplanet:7.4.0", "geoplanet:7.4.1", "geoplanet:7.5.1", "geoplanet:7.5.2", "geoplanet:7.6.0", "geoplanet:7.8.1", "geoplanet:7.9.0", "geoplanet:7.10.0", "geoplanet:8.0.0", "woeplanet:8.0.0"], "meta:indexed": "2020-08-20T20:15:34.036908", "woe:alias_ENG_V": ["HZL Airport", "Hazleton Airport", "Hazleton Municipal", "HZL", "Hazleton Muni Airport"], "meta:updated": "2020-10-14T11:44:08.047862", "woe:hierarchy": {"continent": 24865672, "country": 23424977, "town": 0, "planet": 1, "county": 12589767, "suburb": 0, "state": 2347597, "region": 0, "localadmin": 0}, "woe:timezone_id": 56043648, "woe:hash": "dr3cntxz14fm", "woe:centroid": [-75.992729, 40.988461], "geom:latitude": 40.988461, "geom:longitude": -75.992729, "geom:hash": "dr3cntxz14fm", "woe:latitude": 40.988461, "geom:centroid": [-75.992729, 40.988461], "woe:longitude": -75.992729, "woe:repo": "woeplanet-airport-us", "geom:area": 0.0, "woe:scale": 19}}