{"type": "Feature", "id": 29387796, "geometry": {"type": "Point", "coordinates": [-120.481827, 47.513771]}, "properties": {"woe:id": 29387796, "woe:parent_id": 2375965, "woe:name": "Cashmere-Dryden Airport", "woe:placetype": 14, "woe:placetype_name": "Airport", "woe:lang": "ENG", "iso:country": "US", "meta:provider": ["geoplanet:7.3.1", "geoplanet:7.3.2", "geoplanet:7.4.0", "geoplanet:7.4.1", "geoplanet:7.5.1", "geoplanet:7.5.2", "geoplanet:7.6.0", "geoplanet:7.8.1", "geoplanet:7.9.0", "geoplanet:7.10.0", "geoplanet:8.0.0", "woeplanet:8.0.0"], "meta:indexed": "2020-08-20T20:15:35.359890", "woe:alias_ENG_V": ["8s2"], "meta:updated": "2020-10-14T11:44:07.153508", "woe:hierarchy": {"continent": 24865672, "country": 23424977, "town": 0, "planet": 1, "county": 12590443, "suburb": 0, "state": 2347606, "region": 0, "localadmin": 0}, "woe:timezone_id": 56043663, "woe:hash": "c26q63egcbyk", "woe:centroid": [-120.481827, 47.513771], "geom:latitude": 47.513771, "geom:longitude": -120.481827, "geom:hash": "c26q63egcbyk", "woe:latitude": 47.513771, "geom:centroid": [-120.481827, 47.513771], "woe:longitude": -120.481827, "woe:repo": "woeplanet-airport-us", "geom:area": 0.0, "woe:scale": 19}}