{"type": "Feature", "id": 12519600, "properties": {"woe:id": 12519600, "woe:parent_id": 2387158, "woe:name": "Eglin Air Force Auxiliary Base Nr 3 Duke", "woe:placetype": 14, "woe:placetype_name": "Airport", "woe:lang": "ENG", "iso:country": "US", "meta:provider": ["geoplanet:7.3.1", "geoplanet:7.3.2", "geoplanet:7.4.0", "geoplanet:7.4.1", "geoplanet:7.5.1", "geoplanet:7.5.2", "geoplanet:7.6.0", "geoplanet:7.8.1", "geoplanet:7.9.0", "geoplanet:7.10.0", "geoplanet:8.0.0", "woeplanet:8.0.0"], "meta:indexed": "2020-08-20T20:15:31.946882", "woe:alias_ENG_V": ["Eglin Force Auxiliary Base Nr 3 Duke", "Eglin Force Auxiliary Nr 3 Duke", "EGI", "EGI Airport", "Eglin Air Auxiliary Base Nr 3 Duke", "Eglin Air Auxiliary Nr 3 Duke", "Eglin Air Force Auxiliary Nr 3 Duke", "Eglin Auxiliary Base Nr 3 Duke", "Eglin Auxiliary Nr 3 Duke"], "meta:updated": "2020-08-22T02:54:57.429749", "woe:hierarchy": {"continent": 24865672, "country": 23424977, "town": 0, "planet": 1, "county": 12587848, "suburb": 0, "state": 2347568, "region": 0, "localadmin": 0}, "woe:timezone_id": 56043661, "woe:hash": "dj6qr5gz1dg4", "woe:centroid": [-86.523102, 30.651699], "geom:latitude": 30.651699, "geom:longitude": -86.523102, "geom:hash": "dj6qr5gz1dg4", "woe:latitude": 30.651699, "geom:centroid": [-86.523102, 30.651699], "woe:longitude": -86.523102, "woe:repo": "woeplanet-airport-us"}, "geometry": {"coordinates": [-86.523102, 30.651699], "type": "Point"}}