{"type": "Feature", "id": 29387797, "properties": {"woe:id": 29387797, "woe:parent_id": 2426621, "woe:name": "Port of Ilwaco Airport", "woe:placetype": 14, "woe:placetype_name": "Airport", "woe:lang": "ENG", "iso:country": "US", "meta:provider": ["geoplanet:7.3.1", "geoplanet:7.3.2", "geoplanet:7.4.0", "geoplanet:7.4.1", "geoplanet:7.5.1", "geoplanet:7.5.2", "geoplanet:7.6.0", "geoplanet:7.8.1", "geoplanet:7.9.0", "geoplanet:7.10.0", "geoplanet:8.0.0", "woeplanet:8.0.0"], "meta:indexed": "2020-08-20T20:15:35.360840", "woe:alias_ENG_V": ["7w1"], "meta:updated": "2020-08-22T02:54:59.766136", "woe:hierarchy": {"continent": 24865672, "country": 23424977, "town": 0, "planet": 1, "county": 12590464, "suburb": 0, "state": 2347606, "region": 0, "localadmin": 0}, "woe:timezone_id": 56043663, "woe:hash": "c0pz6ppmnymv", "woe:centroid": [-124.003418, 46.313759], "geom:latitude": 46.313759, "geom:longitude": -124.003418, "geom:hash": "c0pz6ppmnymv", "woe:latitude": 46.313759, "geom:centroid": [-124.003418, 46.313759], "woe:longitude": -124.003418, "woe:repo": "woeplanet-airport-us"}, "geometry": {"coordinates": [-124.003418, 46.313759], "type": "Point"}}