{"type": "Feature", "id": 12521184, "properties": {"woe:id": 12521184, "woe:parent_id": 2463765, "woe:name": "Oakridge State Airport", "woe:placetype": 14, "woe:placetype_name": "Airport", "woe:lang": "ENG", "iso:country": "US", "meta:provider": ["geoplanet:7.3.1", "geoplanet:7.3.2", "geoplanet:7.4.0", "geoplanet:7.4.1", "geoplanet:7.5.1", "geoplanet:7.5.2", "geoplanet:7.6.0", "geoplanet:7.8.1", "geoplanet:7.9.0", "geoplanet:7.10.0", "geoplanet:8.0.0", "woeplanet:8.0.0"], "meta:indexed": "2020-08-20T20:15:34.603525", "woe:alias_ENG_V": ["5s0"], "meta:updated": "2020-08-22T02:54:59.184772", "woe:hierarchy": {"continent": 24865672, "country": 23424977, "town": 0, "planet": 1, "county": 12589711, "suburb": 0, "state": 2347596, "region": 0, "localadmin": 0}, "woe:timezone_id": 56043663, "woe:hash": "9rbbukz7ry60", "woe:centroid": [-122.498253, 43.75227], "geom:latitude": 43.75227, "geom:longitude": -122.498253, "geom:hash": "9rbbukz7ry60", "woe:latitude": 43.75227, "geom:centroid": [-122.498253, 43.75227], "woe:longitude": -122.498253, "woe:repo": "woeplanet-airport-us"}, "geometry": {"coordinates": [-122.498253, 43.75227], "type": "Point"}}