{"type": "Feature", "id": 12523396, "geometry": {"type": "Point", "coordinates": [-85.833633, 33.665878]}, "properties": {"woe:id": 12523396, "woe:parent_id": 2354927, "woe:name": "Reilly Army Air Field", "woe:placetype": 14, "woe:placetype_name": "Airport", "woe:lang": "ENG", "iso:country": "US", "meta:provider": ["geoplanet:7.3.1", "geoplanet:7.3.2", "geoplanet:7.4.0", "geoplanet:7.4.1", "geoplanet:7.5.1", "geoplanet:7.5.2", "geoplanet:7.6.0", "geoplanet:7.8.1", "geoplanet:7.9.0", "geoplanet:7.10.0", "geoplanet:8.0.0", "woeplanet:8.0.0"], "meta:indexed": "2020-08-20T20:15:32.752779", "woe:alias_ENG_V": ["Reilly Army Field", "RLI", "RLI Airport", "Reilly Army", "Reilly Army Air"], "meta:updated": "2020-10-14T11:44:08.716432", "woe:hierarchy": {"continent": 24865672, "country": 23424977, "town": 0, "planet": 1, "county": 12587494, "suburb": 0, "state": 2347559, "region": 0, "localadmin": 0}, "woe:timezone_id": 56043661, "woe:hash": "djfzwb9vgqs2", "woe:centroid": [-85.833633, 33.665878], "geom:latitude": 33.665878, "geom:longitude": -85.833633, "geom:hash": "djfzwb9vgqs2", "woe:latitude": 33.665878, "geom:centroid": [-85.833633, 33.665878], "woe:longitude": -85.833633, "woe:repo": "woeplanet-airport-us", "geom:area": 0.0, "woe:scale": 19}}