{"type": "Feature", "id": 12520285, "properties": {"woe:id": 12520285, "woe:parent_id": 2426659, "woe:name": "Imperial Municipal Airport", "woe:placetype": 14, "woe:placetype_name": "Airport", "woe:lang": "ENG", "iso:country": "US", "meta:provider": ["geoplanet:7.3.1", "geoplanet:7.3.2", "geoplanet:7.4.0", "geoplanet:7.4.1", "geoplanet:7.5.1", "geoplanet:7.5.2", "geoplanet:7.6.0", "geoplanet:7.8.1", "geoplanet:7.9.0", "geoplanet:7.10.0", "geoplanet:8.0.0", "woeplanet:8.0.0"], "meta:indexed": "2020-08-20T20:15:34.117082", "woe:alias_ENG_V": ["Imperial Municipal", "IML", "IML Airport", "Imperial Airport", "Imperial Muni Airport"], "meta:updated": "2020-08-22T02:54:58.959645", "woe:hierarchy": {"continent": 24865672, "country": 23424977, "town": 0, "planet": 1, "county": 12589152, "suburb": 0, "state": 2347586, "region": 0, "localadmin": 0}, "woe:timezone_id": 56043665, "woe:hash": "9xpwrrhb50b2", "woe:centroid": [-101.627869, 40.512089], "geom:latitude": 40.512089, "geom:longitude": -101.627869, "geom:hash": "9xpwrrhb50b2", "woe:latitude": 40.512089, "geom:centroid": [-101.627869, 40.512089], "woe:longitude": -101.627869, "woe:repo": "woeplanet-airport-us"}, "geometry": {"coordinates": [-101.627869, 40.512089], "type": "Point"}}