{"type": "Feature", "id": 12520778, "geometry": {"type": "Point", "coordinates": [-86.255791, 44.275681]}, "properties": {"woe:id": 12520778, "woe:parent_id": 2459486, "woe:name": "Manistee County-Blacker Airport", "woe:placetype": 14, "woe:placetype_name": "Airport", "woe:lang": "ENG", "iso:country": "US", "meta:provider": ["geoplanet:7.3.1", "geoplanet:7.3.2", "geoplanet:7.4.0", "geoplanet:7.4.1", "geoplanet:7.5.1", "geoplanet:7.5.2", "geoplanet:7.6.0", "geoplanet:7.8.1", "geoplanet:7.9.0", "geoplanet:7.10.0", "geoplanet:8.0.0", "woeplanet:8.0.0"], "meta:indexed": "2020-08-20T20:15:34.375001", "woe:alias_ENG_V": ["Blacker Airport", "Manistee-Blacker Airport", "MBL", "MBL Airport", "Manistee County-Blacker", "Manistee-Blacker", "Manistee Co.-blacker Airport"], "meta:updated": "2020-10-14T11:44:07.839345", "woe:hierarchy": {"continent": 24865672, "country": 23424977, "town": 0, "planet": 1, "county": 12588764, "suburb": 0, "state": 2347581, "region": 0, "localadmin": 0}, "woe:timezone_id": 56043658, "woe:hash": "dpfevhnkw3hs", "woe:centroid": [-86.255791, 44.275681], "geom:latitude": 44.275681, "geom:longitude": -86.255791, "geom:hash": "dpfevhnkw3hs", "woe:latitude": 44.275681, "geom:centroid": [-86.255791, 44.275681], "woe:longitude": -86.255791, "woe:repo": "woeplanet-airport-us", "geom:area": 0.0, "woe:scale": 19}}