{"type": "Feature", "id": 12519130, "properties": {"woe:id": 12519130, "woe:parent_id": 2479249, "woe:name": "Chambersburg Municipal Airport", "woe:placetype": 14, "woe:placetype_name": "Airport", "woe:lang": "ENG", "iso:country": "US", "meta:provider": ["geoplanet:7.3.1", "geoplanet:7.3.2", "geoplanet:7.4.0", "geoplanet:7.4.1", "geoplanet:7.5.1", "geoplanet:7.5.2", "geoplanet:7.6.0", "geoplanet:7.8.1", "geoplanet:7.9.0", "geoplanet:7.10.0", "geoplanet:8.0.0", "woeplanet:8.0.0"], "meta:indexed": "2020-08-20T20:15:33.468294", "woe:alias_ENG_V": ["Franklin County Regional Airport", "N68", "Franklin County Rgnl Airport"], "meta:updated": "2020-08-22T02:54:58.658816", "woe:hierarchy": {"continent": 24865672, "country": 23424977, "town": 0, "planet": 1, "county": 12589755, "suburb": 0, "state": 2347597, "region": 0, "localadmin": 0}, "woe:timezone_id": 56043648, "woe:hash": "dr0g3hfc5scz", "woe:centroid": [-77.647438, 39.97258], "geom:latitude": 39.97258, "geom:longitude": -77.647438, "geom:hash": "dr0g3hfc5scz", "woe:latitude": 39.97258, "geom:centroid": [-77.647438, 39.97258], "woe:longitude": -77.647438, "woe:repo": "woeplanet-airport-us"}, "geometry": {"coordinates": [-77.647438, 39.97258], "type": "Point"}}