{"type": "Feature", "id": 12519828, "properties": {"woe:id": 12519828, "woe:parent_id": 2407598, "woe:name": "Friday Harbor Airport", "woe:placetype": 14, "woe:placetype_name": "Airport", "woe:lang": "ENG", "iso:country": "US", "meta:provider": ["geoplanet:7.3.1", "geoplanet:7.3.2", "geoplanet:7.4.0", "geoplanet:7.4.1", "geoplanet:7.5.1", "geoplanet:7.5.2", "geoplanet:7.6.0", "geoplanet:7.8.1", "geoplanet:7.9.0", "geoplanet:7.10.0", "geoplanet:8.0.0", "woeplanet:8.0.0"], "meta:indexed": "2020-08-20T20:15:33.865706", "woe:alias_ENG_V": ["FRD Airport", "FRD", "FHR"], "meta:updated": "2020-08-22T02:54:58.837780", "woe:hierarchy": {"continent": 24865672, "country": 23424977, "town": 0, "planet": 1, "county": 12590467, "suburb": 0, "state": 2347606, "region": 0, "localadmin": 0}, "woe:timezone_id": 56043663, "woe:hash": "c28s03wrfdvq", "woe:centroid": [-123.027191, 48.525211], "geom:latitude": 48.525211, "geom:longitude": -123.027191, "geom:hash": "c28s03wrfdvq", "woe:latitude": 48.525211, "geom:centroid": [-123.027191, 48.525211], "woe:longitude": -123.027191, "woe:repo": "woeplanet-airport-us"}, "geometry": {"coordinates": [-123.027191, 48.525211], "type": "Point"}}