{"type": "Feature", "id": 29387923, "properties": {"woe:id": 29387923, "woe:parent_id": 2514975, "woe:name": "Waskish Municipal Airport", "woe:placetype": 14, "woe:placetype_name": "Airport", "woe:lang": "ENG", "iso:country": "US", "meta:provider": ["geoplanet:7.3.1", "geoplanet:7.3.2", "geoplanet:7.4.0", "geoplanet:7.4.1", "geoplanet:7.5.1", "geoplanet:7.5.2", "geoplanet:7.6.0", "geoplanet:7.8.1", "geoplanet:7.9.0", "geoplanet:7.10.0", "geoplanet:8.0.0", "woeplanet:8.0.0"], "meta:indexed": "2020-08-20T20:15:35.455481", "woe:alias_ENG_V": ["Vwu", "Waskish Muni Airport"], "meta:updated": "2020-08-22T02:54:58.206754", "woe:hierarchy": {"continent": 24865672, "country": 23424977, "town": 0, "planet": 1, "county": 12588800, "suburb": 0, "state": 2347582, "region": 0, "localadmin": 0}, "woe:timezone_id": 56043661, "woe:hash": "cbscchsxy6k8", "woe:centroid": [-94.519913, 48.146179], "geom:latitude": 48.146179, "geom:longitude": -94.519913, "geom:hash": "cbscchsxy6k8", "woe:latitude": 48.146179, "geom:centroid": [-94.519913, 48.146179], "woe:longitude": -94.519913, "woe:repo": "woeplanet-airport-us"}, "geometry": {"coordinates": [-94.519913, 48.146179], "type": "Point"}}