{"type": "Feature", "id": 12520055, "properties": {"woe:id": 12520055, "woe:parent_id": 2466246, "woe:name": "Haigh Field Airport", "woe:placetype": 14, "woe:placetype_name": "Airport", "woe:lang": "ENG", "iso:country": "US", "meta:provider": ["geoplanet:7.3.1", "geoplanet:7.3.2", "geoplanet:7.4.0", "geoplanet:7.4.1", "geoplanet:7.5.1", "geoplanet:7.5.2", "geoplanet:7.6.0", "geoplanet:7.8.1", "geoplanet:7.9.0", "geoplanet:7.10.0", "geoplanet:8.0.0", "woeplanet:8.0.0"], "meta:indexed": "2020-08-20T20:15:32.070121", "meta:updated": "2020-08-22T02:54:57.495703", "woe:alias_ENG_V": ["Haigh Field", "O37"], "woe:hierarchy": {"continent": 24865672, "country": 23424977, "town": 0, "planet": 1, "county": 12587680, "suburb": 0, "state": 2347563, "region": 0, "localadmin": 0}, "woe:timezone_id": 56043663, "woe:hash": "9r11ux09bjvd", "woe:centroid": [-122.145302, 39.721401], "geom:latitude": 39.721401, "geom:longitude": -122.145302, "geom:hash": "9r11ux09bjvd", "woe:latitude": 39.721401, "geom:centroid": [-122.145302, 39.721401], "woe:longitude": -122.145302, "woe:repo": "woeplanet-airport-us"}, "geometry": {"coordinates": [-122.145302, 39.721401], "type": "Point"}}