{"type": "Feature", "id": 12519587, "geometry": {"type": "Point", "coordinates": [-114.463493, 36.311771]}, "properties": {"woe:id": 12519587, "woe:parent_id": 2396829, "woe:name": "Echo Bay Airport", "woe:placetype": 14, "woe:placetype_name": "Airport", "woe:lang": "ENG", "iso:country": "US", "meta:provider": ["geoplanet:7.3.1", "geoplanet:7.3.2", "geoplanet:7.4.0", "geoplanet:7.4.1", "geoplanet:7.5.1", "geoplanet:7.5.2", "geoplanet:7.6.0", "geoplanet:7.8.1", "geoplanet:7.9.0", "geoplanet:7.10.0", "geoplanet:8.0.0", "woeplanet:8.0.0"], "meta:indexed": "2020-08-20T20:15:33.741031", "woe:alias_ENG_V": ["0l9"], "meta:updated": "2020-10-14T11:44:08.736332", "woe:hierarchy": {"continent": 24865672, "country": 23424977, "town": 0, "planet": 1, "county": 12589233, "suburb": 0, "state": 2347587, "region": 0, "localadmin": 0}, "woe:timezone_id": 56043663, "woe:hash": "9qqwe665rk9x", "woe:centroid": [-114.463493, 36.311771], "geom:latitude": 36.311771, "geom:longitude": -114.463493, "geom:hash": "9qqwe665rk9x", "woe:latitude": 36.311771, "geom:centroid": [-114.463493, 36.311771], "woe:longitude": -114.463493, "woe:repo": "woeplanet-airport-us", "geom:area": 0.0, "woe:scale": 19}}