{"type": "Feature", "id": 12520834, "geometry": {"type": "Point", "coordinates": [-86.410019, 43.9571]}, "properties": {"woe:id": 12520834, "woe:parent_id": 28744310, "woe:name": "Mason County Airport", "woe:placetype": 14, "woe:placetype_name": "Airport", "woe:lang": "ENG", "iso:country": "US", "meta:provider": ["geoplanet:7.3.1", "geoplanet:7.3.2", "geoplanet:7.4.0", "geoplanet:7.4.1", "geoplanet:7.5.1", "geoplanet:7.5.2", "geoplanet:7.6.0", "geoplanet:7.8.1", "geoplanet:7.9.0", "geoplanet:7.10.0", "geoplanet:8.0.0", "woeplanet:8.0.0"], "meta:indexed": "2020-08-20T20:15:34.407051", "woe:alias_ENG_V": ["Ldm"], "meta:updated": "2020-10-14T11:44:09.327679", "woe:hierarchy": {"continent": 24865672, "country": 23424977, "town": 0, "planet": 1, "county": 12588766, "suburb": 0, "state": 2347581, "region": 0, "localadmin": 0}, "woe:timezone_id": 56043658, "woe:hash": "dpfd1dnhst7g", "woe:centroid": [-86.410019, 43.9571], "geom:latitude": 43.9571, "geom:longitude": -86.410019, "geom:hash": "dpfd1dnhst7g", "woe:latitude": 43.9571, "geom:centroid": [-86.410019, 43.9571], "woe:longitude": -86.410019, "woe:repo": "woeplanet-airport-us", "geom:area": 0.0, "woe:scale": 19}}