{"type": "Feature", "id": 12520863, "properties": {"woe:id": 12520863, "woe:parent_id": 2469737, "woe:name": "Mckinley Field Airport", "woe:placetype": 14, "woe:placetype_name": "Airport", "woe:lang": "ENG", "iso:country": "US", "meta:provider": ["geoplanet:7.3.1", "geoplanet:7.3.2", "geoplanet:7.4.0", "geoplanet:7.4.1", "geoplanet:7.5.1", "geoplanet:7.5.2", "geoplanet:7.6.0", "geoplanet:7.8.1", "geoplanet:7.9.0", "geoplanet:7.10.0", "geoplanet:8.0.0", "woeplanet:8.0.0"], "meta:indexed": "2020-08-20T20:15:34.421413", "woe:alias_ENG_V": ["Mckinley Field", "T30"], "meta:updated": "2020-08-22T02:54:59.100034", "woe:hierarchy": {"continent": 24865672, "country": 23424977, "town": 0, "planet": 1, "county": 12590088, "suburb": 0, "state": 2347602, "region": 0, "localadmin": 0}, "woe:timezone_id": 56043661, "woe:hash": "9v1ebxfd9j4r", "woe:centroid": [-99.115173, 28.827209], "geom:latitude": 28.827209, "geom:longitude": -99.115173, "geom:hash": "9v1ebxfd9j4r", "woe:latitude": 28.827209, "geom:centroid": [-99.115173, 28.827209], "woe:longitude": -99.115173, "woe:repo": "woeplanet-airport-us"}, "geometry": {"coordinates": [-99.115173, 28.827209], "type": "Point"}}