{"type": "Feature", "id": 23418438, "geometry": {"type": "Point", "coordinates": [-74.702293, 41.617531]}, "properties": {"woe:id": 23418438, "woe:parent_id": 28744956, "woe:name": "Monticello Airport", "woe:placetype": 14, "woe:placetype_name": "Airport", "woe:lang": "ENG", "iso:country": "US", "meta:provider": ["geoplanet:7.3.1", "geoplanet:7.3.2", "geoplanet:7.4.0", "geoplanet:7.4.1", "geoplanet:7.5.1", "geoplanet:7.5.2", "geoplanet:7.6.0", "geoplanet:7.8.1", "geoplanet:7.9.0", "geoplanet:7.10.0", "geoplanet:8.0.0", "woeplanet:8.0.0"], "meta:indexed": "2020-08-20T20:15:35.313071", "woe:alias_ENG_V": ["N37"], "meta:updated": "2020-10-14T11:44:06.708330", "woe:hierarchy": {"continent": 24865672, "country": 23424977, "town": 0, "planet": 1, "county": 12589364, "suburb": 0, "state": 2347591, "region": 0, "localadmin": 0}, "woe:timezone_id": 56043648, "woe:hash": "dr6uu05rwqj4", "woe:centroid": [-74.702293, 41.617531], "geom:latitude": 41.617531, "geom:longitude": -74.702293, "geom:hash": "dr6uu05rwqj4", "woe:latitude": 41.617531, "geom:centroid": [-74.702293, 41.617531], "woe:longitude": -74.702293, "woe:repo": "woeplanet-airport-us", "geom:area": 0.0, "woe:scale": 19}}