{"type": "Feature", "id": 12521181, "properties": {"woe:id": 12521181, "woe:parent_id": 2515094, "woe:name": "Oakland County International Airport", "woe:placetype": 14, "woe:placetype_name": "Airport", "woe:lang": "ENG", "iso:country": "US", "meta:provider": ["geoplanet:7.3.1", "geoplanet:7.3.2", "geoplanet:7.4.0", "geoplanet:7.4.1", "geoplanet:7.5.1", "geoplanet:7.5.2", "geoplanet:7.6.0", "geoplanet:7.8.1", "geoplanet:7.9.0", "geoplanet:7.10.0", "geoplanet:8.0.0", "woeplanet:8.0.0"], "meta:indexed": "2020-08-20T20:15:34.601332", "woe:alias_ENG_V": ["Oakland County Int'l Airport", "Oakland Airport", "Oakland County Airport", "Oakland Pontiac Airport", "Oakland County International", "Oakland International", "Oakland International Airport", "PTK", "PTK Airport"], "meta:updated": "2020-08-22T02:54:59.183936", "woe:hierarchy": {"continent": 24865672, "country": 23424977, "town": 0, "planet": 1, "county": 12588776, "suburb": 0, "state": 2347581, "region": 0, "localadmin": 0}, "woe:timezone_id": 56043658, "woe:hash": "dpsdty98kmqp", "woe:centroid": [-83.416939, 42.662731], "geom:latitude": 42.662731, "geom:longitude": -83.416939, "geom:hash": "dpsdty98kmqp", "woe:latitude": 42.662731, "geom:centroid": [-83.416939, 42.662731], "woe:longitude": -83.416939, "woe:repo": "woeplanet-airport-us"}, "geometry": {"coordinates": [-83.416939, 42.662731], "type": "Point"}}