{"type": "Feature", "id": 12521070, "geometry": {"type": "Point", "coordinates": [-87.6185, 34.743889]}, "properties": {"woe:id": 12521070, "woe:parent_id": 2456572, "woe:name": "Muscle Shoals Regional Airport", "woe:placetype": 14, "woe:placetype_name": "Airport", "woe:lang": "ENG", "iso:country": "US", "meta:provider": ["geoplanet:7.3.1", "geoplanet:7.3.2", "geoplanet:7.4.0", "geoplanet:7.4.1", "geoplanet:7.5.1", "geoplanet:7.5.2", "geoplanet:7.6.0", "geoplanet:7.8.1", "geoplanet:7.9.0", "geoplanet:7.10.0", "geoplanet:8.0.0", "woeplanet:8.0.0"], "meta:indexed": "2020-08-20T20:15:34.536543", "woe:alias_ENG_V": ["Muscle Shoals Airport", "Muscle Shoals Regional", "MSL", "MSL Airport", "Northwest Alabama Regional Airport", "Northwest Alabama Rgnl Airport"], "meta:updated": "2020-10-14T11:44:09.108851", "woe:hierarchy": {"continent": 24865672, "country": 23424977, "town": 0, "planet": 1, "county": 12587503, "suburb": 0, "state": 2347559, "region": 0, "localadmin": 0}, "woe:timezone_id": 56043661, "woe:hash": "dn1twhyjufr4", "woe:centroid": [-87.6185, 34.743889], "geom:latitude": 34.743889, "geom:longitude": -87.6185, "geom:hash": "dn1twhyjufr4", "woe:latitude": 34.743889, "geom:centroid": [-87.6185, 34.743889], "woe:longitude": -87.6185, "woe:repo": "woeplanet-airport-us", "geom:area": 0.0, "woe:scale": 19}}