{"type": "Feature", "id": 12520623, "properties": {"woe:id": 12520623, "woe:parent_id": 2371160, "woe:name": "Lehigh Acres West Airport", "woe:placetype": 14, "woe:placetype_name": "Airport", "woe:lang": "ENG", "iso:country": "US", "meta:provider": ["geoplanet:7.3.1", "geoplanet:7.3.2", "geoplanet:7.4.0", "geoplanet:7.4.1", "geoplanet:7.5.1", "geoplanet:7.5.2", "geoplanet:7.6.0", "geoplanet:7.8.1", "geoplanet:7.9.0", "geoplanet:7.10.0", "geoplanet:8.0.0", "woeplanet:8.0.0"], "meta:indexed": "2020-08-20T20:15:32.217031", "meta:updated": "2020-08-22T02:54:57.572913", "woe:hierarchy": {"continent": 24865672, "country": 23424977, "town": 0, "planet": 1, "county": 12587838, "suburb": 0, "state": 2347568, "region": 0, "localadmin": 0}, "woe:timezone_id": 56043648, "woe:hash": "dhtzsdhpkfp0", "woe:centroid": [-81.710602, 26.643101], "geom:latitude": 26.643101, "geom:longitude": -81.710602, "geom:hash": "dhtzsdhpkfp0", "woe:latitude": 26.643101, "geom:centroid": [-81.710602, 26.643101], "woe:longitude": -81.710602, "woe:repo": "woeplanet-airport-us"}, "geometry": {"coordinates": [-81.710602, 26.643101], "type": "Point"}}