{"type": "Feature", "id": 12518654, "properties": {"woe:id": 12518654, "woe:parent_id": 2409458, "woe:name": "Ardmore Municipal Airport", "woe:placetype": 14, "woe:placetype_name": "Airport", "woe:lang": "ENG", "iso:country": "US", "meta:provider": ["geoplanet:7.3.1", "geoplanet:7.3.2", "geoplanet:7.4.0", "geoplanet:7.4.1", "geoplanet:7.5.1", "geoplanet:7.5.2", "geoplanet:7.6.0", "geoplanet:7.8.1", "geoplanet:7.9.0", "geoplanet:7.10.0", "geoplanet:8.0.0", "woeplanet:8.0.0"], "meta:indexed": "2020-08-20T20:15:33.160583", "woe:alias_ENG_V": ["Ardmore Municipal", "ADM", "ADM Airport", "Ardmore Airport", "Ardmore Muni Airport"], "meta:updated": "2020-08-22T02:54:58.548741", "woe:hierarchy": {"continent": 24865672, "country": 23424977, "town": 0, "planet": 1, "county": 12589624, "suburb": 0, "state": 2347595, "region": 0, "localadmin": 0}, "woe:timezone_id": 56043661, "woe:hash": "9y5504fr8dw3", "woe:centroid": [-97.02813, 34.293751], "geom:latitude": 34.293751, "geom:longitude": -97.02813, "geom:hash": "9y5504fr8dw3", "woe:latitude": 34.293751, "geom:centroid": [-97.02813, 34.293751], "woe:longitude": -97.02813, "woe:repo": "woeplanet-airport-us"}, "geometry": {"coordinates": [-97.02813, 34.293751], "type": "Point"}}