{"type": "Feature", "id": 12519021, "geometry": {"type": "Point", "coordinates": [-72.792503, 40.915001]}, "properties": {"woe:id": 12519021, "woe:parent_id": 2482070, "woe:name": "Calverton Naval Weapons Industrial Reserve Airport", "woe:placetype": 14, "woe:placetype_name": "Airport", "woe:lang": "ENG", "iso:country": "US", "meta:provider": ["geoplanet:7.3.1", "geoplanet:7.3.2", "geoplanet:7.4.0", "geoplanet:7.4.1", "geoplanet:7.5.1", "geoplanet:7.5.2", "geoplanet:7.6.0", "geoplanet:7.8.1", "geoplanet:7.9.0", "geoplanet:7.10.0", "geoplanet:8.0.0", "woeplanet:8.0.0"], "meta:indexed": "2020-08-20T20:15:31.797631", "woe:alias_ENG_V": ["CTO", "CTO Airport", "Calverton Naval Weapons Industrial Reserve"], "meta:updated": "2020-10-14T11:44:08.858339", "woe:hierarchy": {"continent": 24865672, "country": 23424977, "town": 0, "planet": 1, "county": 12589363, "suburb": 0, "state": 2347591, "region": 0, "localadmin": 0}, "woe:timezone_id": 56043648, "woe:hash": "drk0z8655szx", "woe:centroid": [-72.792503, 40.915001], "geom:latitude": 40.915001, "geom:longitude": -72.792503, "geom:hash": "drk0z8655szx", "woe:latitude": 40.915001, "geom:centroid": [-72.792503, 40.915001], "woe:longitude": -72.792503, "woe:repo": "woeplanet-airport-us", "geom:area": 0.0, "woe:scale": 19}}