{"type": "Feature", "id": 12523383, "geometry": {"type": "Point", "coordinates": [-117.643021, 34.12254]}, "properties": {"woe:id": 12523383, "woe:parent_id": 2510215, "woe:name": "Cable Heliport", "woe:placetype": 14, "woe:placetype_name": "Airport", "woe:lang": "ENG", "iso:country": "US", "meta:provider": ["geoplanet:7.3.1", "geoplanet:7.3.2", "geoplanet:7.4.0", "geoplanet:7.4.1", "geoplanet:7.5.1", "geoplanet:7.5.2", "geoplanet:7.6.0", "geoplanet:7.8.1", "geoplanet:7.9.0", "geoplanet:7.10.0", "geoplanet:8.0.0", "woeplanet:8.0.0"], "meta:indexed": "2020-08-20T20:15:32.748154", "woe:alias_ENG_V": ["JUP Airport", "JUP"], "meta:updated": "2020-10-14T11:44:08.710125", "woe:hierarchy": {"continent": 24865672, "country": 23424977, "town": 0, "planet": 1, "county": 12587705, "suburb": 0, "state": 2347563, "region": 0, "localadmin": 0}, "woe:timezone_id": 56043663, "woe:hash": "9qh64gyfnymx", "woe:centroid": [-117.643021, 34.12254], "geom:latitude": 34.12254, "geom:longitude": -117.643021, "geom:hash": "9qh64gyfnymx", "woe:latitude": 34.12254, "geom:centroid": [-117.643021, 34.12254], "woe:longitude": -117.643021, "woe:repo": "woeplanet-airport-us", "geom:area": 0.0, "woe:scale": 19}}