{"type": "Feature", "id": 12518527, "properties": {"woe:id": 12518527, "woe:parent_id": 2398350, "woe:name": "Addington Field Airport", "woe:placetype": 14, "woe:placetype_name": "Airport", "woe:lang": "ENG", "iso:country": "US", "meta:provider": ["geoplanet:7.3.1", "geoplanet:7.3.2", "geoplanet:7.4.0", "geoplanet:7.4.1", "geoplanet:7.5.1", "geoplanet:7.5.2", "geoplanet:7.6.0", "geoplanet:7.8.1", "geoplanet:7.9.0", "geoplanet:7.10.0", "geoplanet:8.0.0", "woeplanet:8.0.0"], "meta:indexed": "2020-08-20T20:15:33.083321", "woe:alias_ENG_V": ["Addington Field Hardin", "EKX", "EKX Airport", "Addington Airport", "Addington Field", "Addington Field Hardin Airport"], "meta:updated": "2020-08-22T02:54:58.518251", "woe:hierarchy": {"continent": 24865672, "country": 23424977, "town": 0, "planet": 1, "county": 12588522, "suburb": 0, "state": 2347576, "region": 0, "localadmin": 0}, "woe:timezone_id": 56043647, "woe:hash": "dndykv24cj4r", "woe:centroid": [-85.924026, 37.690472], "geom:latitude": 37.690472, "geom:longitude": -85.924026, "geom:hash": "dndykv24cj4r", "woe:latitude": 37.690472, "geom:centroid": [-85.924026, 37.690472], "woe:longitude": -85.924026, "woe:repo": "woeplanet-airport-us"}, "geometry": {"coordinates": [-85.924026, 37.690472], "type": "Point"}}