{"type": "Feature", "id": 12520724, "geometry": {"type": "Point", "coordinates": [-79.060211, 34.614449]}, "properties": {"woe:id": 12520724, "woe:parent_id": 2443050, "woe:name": "Lumberton Municipal Airport", "woe:placetype": 14, "woe:placetype_name": "Airport", "woe:lang": "ENG", "iso:country": "US", "meta:provider": ["geoplanet:7.3.1", "geoplanet:7.3.2", "geoplanet:7.4.0", "geoplanet:7.4.1", "geoplanet:7.5.1", "geoplanet:7.5.2", "geoplanet:7.6.0", "geoplanet:7.8.1", "geoplanet:7.9.0", "geoplanet:7.10.0", "geoplanet:8.0.0", "woeplanet:8.0.0"], "meta:indexed": "2020-08-20T20:15:34.345366", "woe:alias_ENG_V": ["Lumberton Municipal", "LBT", "LBT Airport", "Lumberton Airport", "Lumberton Muni Airport"], "meta:updated": "2020-10-14T11:44:07.851962", "woe:hierarchy": {"continent": 24865672, "country": 23424977, "town": 0, "planet": 1, "county": 12589451, "suburb": 0, "state": 2347592, "region": 0, "localadmin": 0}, "woe:timezone_id": 56043648, "woe:hash": "dnpubvq5g8cz", "woe:centroid": [-79.060211, 34.614449], "geom:latitude": 34.614449, "geom:longitude": -79.060211, "geom:hash": "dnpubvq5g8cz", "woe:latitude": 34.614449, "geom:centroid": [-79.060211, 34.614449], "woe:longitude": -79.060211, "woe:repo": "woeplanet-airport-us", "geom:area": 0.0, "woe:scale": 19}}