{"type": "Feature", "id": 12520709, "properties": {"woe:id": 12520709, "woe:parent_id": 2475046, "woe:name": "Lost Mine Airport", "woe:placetype": 14, "woe:placetype_name": "Airport", "woe:lang": "ENG", "iso:country": "US", "meta:provider": ["geoplanet:7.3.1", "geoplanet:7.3.2", "geoplanet:7.4.0", "geoplanet:7.4.1", "geoplanet:7.5.1", "geoplanet:7.5.2", "geoplanet:7.6.0", "geoplanet:7.8.1", "geoplanet:7.9.0", "geoplanet:7.10.0", "geoplanet:8.0.0", "woeplanet:8.0.0"], "meta:indexed": "2020-08-20T20:15:32.238028", "meta:updated": "2020-08-22T02:54:57.582154", "woe:hierarchy": {"continent": 24865672, "country": 23424977, "town": 0, "planet": 1, "county": 12589042, "suburb": 0, "state": 2347584, "region": 0, "localadmin": 0}, "woe:timezone_id": 56043661, "woe:hash": "9yqpezjweef5", "woe:centroid": [-92.639999, 36.514198], "geom:latitude": 36.514198, "geom:longitude": -92.639999, "geom:hash": "9yqpezjweef5", "woe:latitude": 36.514198, "geom:centroid": [-92.639999, 36.514198], "woe:longitude": -92.639999, "woe:repo": "woeplanet-airport-us"}, "geometry": {"coordinates": [-92.639999, 36.514198], "type": "Point"}}