{"type": "Feature", "id": 12520142, "properties": {"woe:id": 12520142, "woe:parent_id": 2419301, "woe:name": "Hazen Municipal Airport", "woe:placetype": 14, "woe:placetype_name": "Airport", "woe:lang": "ENG", "iso:country": "US", "meta:provider": ["geoplanet:7.3.1", "geoplanet:7.3.2", "geoplanet:7.4.0", "geoplanet:7.4.1", "geoplanet:7.5.1", "geoplanet:7.5.2", "geoplanet:7.6.0", "geoplanet:7.8.1", "geoplanet:7.9.0", "geoplanet:7.10.0", "geoplanet:8.0.0", "woeplanet:8.0.0"], "meta:indexed": "2020-08-20T20:15:34.034543", "woe:alias_ENG_V": ["Hze", "Mercer County Rgnl Airport", "Mercer County Regional Airport"], "meta:updated": "2020-08-22T02:54:58.920182", "woe:hierarchy": {"continent": 24865672, "country": 23424977, "town": 0, "planet": 1, "county": 12589502, "suburb": 0, "state": 2347593, "region": 0, "localadmin": 0}, "woe:timezone_id": 56043665, "woe:hash": "c8rv0d8f2uu0", "woe:centroid": [-101.578522, 47.299301], "geom:latitude": 47.299301, "geom:longitude": -101.578522, "geom:hash": "c8rv0d8f2uu0", "woe:latitude": 47.299301, "geom:centroid": [-101.578522, 47.299301], "woe:longitude": -101.578522, "woe:repo": "woeplanet-airport-us"}, "geometry": {"coordinates": [-101.578522, 47.299301], "type": "Point"}}