{"type": "Feature", "id": 29388140, "geometry": {"type": "Point", "coordinates": [-95.218102, 38.280392]}, "properties": {"woe:id": 29388140, "woe:parent_id": 2409037, "woe:name": "Garnett Municipal Airport", "woe:placetype": 14, "woe:placetype_name": "Airport", "woe:lang": "ENG", "iso:country": "US", "meta:provider": ["geoplanet:7.3.1", "geoplanet:7.3.2", "geoplanet:7.4.0", "geoplanet:7.4.1", "geoplanet:7.5.1", "geoplanet:7.5.2", "geoplanet:7.6.0", "geoplanet:7.8.1", "geoplanet:7.9.0", "geoplanet:7.10.0", "geoplanet:8.0.0", "woeplanet:8.0.0"], "meta:indexed": "2020-08-20T20:15:35.661162", "woe:alias_ENG_V": ["K68", "Garnett Muni Airport"], "meta:updated": "2020-10-14T11:44:07.081572", "woe:hierarchy": {"continent": 24865672, "country": 23424977, "town": 0, "planet": 1, "county": 12588372, "suburb": 0, "state": 2347575, "region": 0, "localadmin": 0}, "woe:timezone_id": 56043661, "woe:hash": "9yu3c28r3qm0", "woe:centroid": [-95.218102, 38.280392], "geom:latitude": 38.280392, "geom:longitude": -95.218102, "geom:hash": "9yu3c28r3qm0", "woe:latitude": 38.280392, "geom:centroid": [-95.218102, 38.280392], "woe:longitude": -95.218102, "woe:repo": "woeplanet-airport-us", "geom:area": 0.0, "woe:scale": 19}}