{"type": "Feature", "id": 12519962, "geometry": {"type": "Point", "coordinates": [-101.728699, 40.866718]}, "properties": {"woe:id": 12519962, "woe:parent_id": 2413123, "woe:name": "Grant Municipal Airport", "woe:placetype": 14, "woe:placetype_name": "Airport", "woe:lang": "ENG", "iso:country": "US", "meta:provider": ["geoplanet:7.3.1", "geoplanet:7.3.2", "geoplanet:7.4.0", "geoplanet:7.4.1", "geoplanet:7.5.1", "geoplanet:7.5.2", "geoplanet:7.6.0", "geoplanet:7.8.1", "geoplanet:7.9.0", "geoplanet:7.10.0", "geoplanet:8.0.0", "woeplanet:8.0.0"], "meta:indexed": "2020-08-20T20:15:33.939246", "woe:alias_ENG_V": ["GGF Airport", "GGF", "Grant Muni Airport"], "meta:updated": "2020-10-14T11:44:08.247580", "woe:hierarchy": {"continent": 24865672, "country": 23424977, "town": 0, "planet": 1, "county": 12589205, "suburb": 0, "state": 2347586, "region": 0, "localadmin": 0}, "woe:timezone_id": 56043665, "woe:hash": "9xr8mpe3vs2h", "woe:centroid": [-101.728699, 40.866718], "geom:latitude": 40.866718, "geom:longitude": -101.728699, "geom:hash": "9xr8mpe3vs2h", "woe:latitude": 40.866718, "geom:centroid": [-101.728699, 40.866718], "woe:longitude": -101.728699, "woe:repo": "woeplanet-airport-us", "geom:area": 0.0, "woe:scale": 19}}