{"type": "Feature", "id": 12521653, "geometry": {"type": "Point", "coordinates": [-84.571701, 44.472939]}, "properties": {"woe:id": 12521653, "woe:parent_id": 2484471, "woe:name": "Roscommon Conservation Airport", "woe:placetype": 14, "woe:placetype_name": "Airport", "woe:lang": "ENG", "iso:country": "US", "meta:provider": ["geoplanet:7.3.1", "geoplanet:7.3.2", "geoplanet:7.4.0", "geoplanet:7.4.1", "geoplanet:7.5.1", "geoplanet:7.5.2", "geoplanet:7.6.0", "geoplanet:7.8.1", "geoplanet:7.9.0", "geoplanet:7.10.0", "geoplanet:8.0.0", "woeplanet:8.0.0"], "meta:indexed": "2020-08-20T20:15:34.841380", "woe:alias_ENG_V": ["3rc"], "meta:updated": "2020-10-14T11:44:07.640345", "woe:hierarchy": {"continent": 24865672, "country": 23424977, "town": 0, "planet": 1, "county": 12588785, "suburb": 0, "state": 2347581, "region": 0, "localadmin": 0}, "woe:timezone_id": 56043658, "woe:hash": "dpgv580c8s9n", "woe:centroid": [-84.571701, 44.472939], "geom:latitude": 44.472939, "geom:longitude": -84.571701, "geom:hash": "dpgv580c8s9n", "woe:latitude": 44.472939, "geom:centroid": [-84.571701, 44.472939], "woe:longitude": -84.571701, "woe:repo": "woeplanet-airport-us", "geom:area": 0.0, "woe:scale": 19}}