{"type": "Feature", "id": 12521238, "geometry": {"type": "Point", "coordinates": [-98.051399, 27.900801]}, "properties": {"woe:id": 12521238, "woe:parent_id": 23418395, "woe:name": "Orange Grove Naval Auxiliary Landing Field", "woe:placetype": 14, "woe:placetype_name": "Airport", "woe:lang": "ENG", "iso:country": "US", "meta:provider": ["geoplanet:7.3.1", "geoplanet:7.3.2", "geoplanet:7.4.0", "geoplanet:7.4.1", "geoplanet:7.5.1", "geoplanet:7.5.2", "geoplanet:7.6.0", "geoplanet:7.8.1", "geoplanet:7.9.0", "geoplanet:7.10.0", "geoplanet:8.0.0", "woeplanet:8.0.0"], "meta:indexed": "2020-08-20T20:15:32.357131", "meta:updated": "2020-10-14T11:44:07.977180", "woe:hierarchy": {"continent": 24865672, "country": 23424977, "town": 0, "planet": 1, "county": 12590131, "suburb": 0, "state": 2347602, "region": 0, "localadmin": 0}, "woe:timezone_id": 56043661, "woe:hash": "9ufq8z1juy3b", "woe:centroid": [-98.051399, 27.900801], "geom:latitude": 27.900801, "geom:longitude": -98.051399, "geom:hash": "9ufq8z1juy3b", "woe:latitude": 27.900801, "geom:centroid": [-98.051399, 27.900801], "woe:longitude": -98.051399, "woe:repo": "woeplanet-airport-us", "geom:area": 0.0, "woe:scale": 19}}