{"type": "Feature", "id": 12519483, "properties": {"woe:id": 12519483, "woe:parent_id": 2391687, "woe:name": "Devine Municipal Airport", "woe:placetype": 14, "woe:placetype_name": "Airport", "woe:lang": "ENG", "iso:country": "US", "meta:provider": ["geoplanet:7.3.1", "geoplanet:7.3.2", "geoplanet:7.4.0", "geoplanet:7.4.1", "geoplanet:7.5.1", "geoplanet:7.5.2", "geoplanet:7.6.0", "geoplanet:7.8.1", "geoplanet:7.9.0", "geoplanet:7.10.0", "geoplanet:8.0.0", "woeplanet:8.0.0"], "meta:indexed": "2020-08-20T20:15:33.687359", "woe:alias_ENG_V": ["23r", "Devine Muni Airport"], "meta:updated": "2020-08-22T02:54:58.751982", "woe:hierarchy": {"continent": 24865672, "country": 23424977, "town": 0, "planet": 1, "county": 12590169, "suburb": 0, "state": 2347602, "region": 0, "localadmin": 0}, "woe:timezone_id": 56043661, "woe:hash": "9v1tu2zmptsw", "woe:centroid": [-98.943573, 29.140751], "geom:latitude": 29.140751, "geom:longitude": -98.943573, "geom:hash": "9v1tu2zmptsw", "woe:latitude": 29.140751, "geom:centroid": [-98.943573, 29.140751], "woe:longitude": -98.943573, "woe:repo": "woeplanet-airport-us"}, "geometry": {"coordinates": [-98.943573, 29.140751], "type": "Point"}}