{"type": "Feature", "id": 12521645, "geometry": {"type": "Point", "coordinates": [-117.874168, 42.586079]}, "properties": {"woe:id": 12521645, "woe:parent_id": 2359828, "woe:name": "Rome State Airport", "woe:placetype": 14, "woe:placetype_name": "Airport", "woe:lang": "ENG", "iso:country": "US", "meta:provider": ["geoplanet:7.3.1", "geoplanet:7.3.2", "geoplanet:7.4.0", "geoplanet:7.4.1", "geoplanet:7.5.1", "geoplanet:7.5.2", "geoplanet:7.6.0", "geoplanet:7.8.1", "geoplanet:7.9.0", "geoplanet:7.10.0", "geoplanet:8.0.0", "woeplanet:8.0.0"], "meta:indexed": "2020-08-20T20:15:34.836093", "woe:alias_ENG_V": ["REO Airport", "Rome State", "REO"], "meta:updated": "2020-10-14T11:44:07.641078", "woe:hierarchy": {"continent": 24865672, "country": 23424977, "town": 0, "planet": 1, "county": 12589714, "suburb": 0, "state": 2347596, "region": 0, "localadmin": 0}, "woe:timezone_id": 56043663, "woe:hash": "9rs4m8w9uu9b", "woe:centroid": [-117.874168, 42.586079], "geom:latitude": 42.586079, "geom:longitude": -117.874168, "geom:hash": "9rs4m8w9uu9b", "woe:latitude": 42.586079, "geom:centroid": [-117.874168, 42.586079], "woe:longitude": -117.874168, "woe:repo": "woeplanet-airport-us", "geom:area": 0.0, "woe:scale": 19}}