{"type": "Feature", "id": 12522462, "properties": {"woe:id": 12522462, "woe:parent_id": 2445764, "woe:name": "Williamson County Regional Airport", "woe:placetype": 14, "woe:placetype_name": "Airport", "woe:lang": "ENG", "iso:country": "US", "meta:provider": ["geoplanet:7.3.1", "geoplanet:7.3.2", "geoplanet:7.4.0", "geoplanet:7.4.1", "geoplanet:7.5.1", "geoplanet:7.5.2", "geoplanet:7.6.0", "geoplanet:7.8.1", "geoplanet:7.9.0", "geoplanet:7.10.0", "geoplanet:8.0.0", "woeplanet:8.0.0"], "meta:indexed": "2020-08-20T20:15:35.236087", "woe:alias_ENG_V": ["MWA", "MWA Airport", "Williamson Airport", "Williamson County Airport", "Williamson County Regional", "Williamson Regional", "Williamson Regional Airport", "Williamson County Rgnl Airport"], "meta:updated": "2020-08-22T02:54:59.712602", "woe:hierarchy": {"continent": 24865672, "country": 23424977, "town": 0, "planet": 1, "county": 12588177, "suburb": 0, "state": 2347572, "region": 0, "localadmin": 0}, "woe:timezone_id": 56043661, "woe:hash": "dn8wwx8d6nuk", "woe:centroid": [-89.010452, 37.7467], "geom:latitude": 37.7467, "geom:longitude": -89.010452, "geom:hash": "dn8wwx8d6nuk", "woe:latitude": 37.7467, "geom:centroid": [-89.010452, 37.7467], "woe:longitude": -89.010452, "woe:repo": "woeplanet-airport-us"}, "geometry": {"coordinates": [-89.010452, 37.7467], "type": "Point"}}