{"type": "Feature", "id": 12518629, "geometry": {"type": "Point", "coordinates": [-93.572891, 41.698761]}, "properties": {"woe:id": 12518629, "woe:parent_id": 2354828, "woe:name": "Ankeny Regional Airport", "woe:placetype": 14, "woe:placetype_name": "Airport", "woe:lang": "ENG", "iso:country": "US", "meta:provider": ["geoplanet:7.3.1", "geoplanet:7.3.2", "geoplanet:7.4.0", "geoplanet:7.4.1", "geoplanet:7.5.1", "geoplanet:7.5.2", "geoplanet:7.6.0", "geoplanet:7.8.1", "geoplanet:7.9.0", "geoplanet:7.10.0", "geoplanet:8.0.0", "woeplanet:8.0.0"], "meta:indexed": "2020-08-20T20:15:31.717458", "woe:alias_ENG_V": ["IKV Airport", "IKV", "Ankeny Rgnl Airport"], "meta:updated": "2020-10-14T11:44:08.647382", "woe:hierarchy": {"continent": 24865672, "country": 23424977, "town": 0, "planet": 1, "county": 12588348, "suburb": 0, "state": 2347574, "region": 0, "localadmin": 0}, "woe:timezone_id": 56043661, "woe:hash": "9zmmnxn2cs7q", "woe:centroid": [-93.572891, 41.698761], "geom:latitude": 41.698761, "geom:longitude": -93.572891, "geom:hash": "9zmmnxn2cs7q", "woe:latitude": 41.698761, "geom:centroid": [-93.572891, 41.698761], "woe:longitude": -93.572891, "woe:repo": "woeplanet-airport-us", "geom:area": 0.0, "woe:scale": 19}}