{"type": "Feature", "id": 12522044, "properties": {"woe:id": 12522044, "woe:parent_id": 2455269, "woe:name": "Summit Airpark", "woe:placetype": 14, "woe:placetype_name": "Airport", "woe:lang": "ENG", "iso:country": "US", "meta:provider": ["geoplanet:7.3.1", "geoplanet:7.3.2", "geoplanet:7.4.0", "geoplanet:7.4.1", "geoplanet:7.5.1", "geoplanet:7.5.2", "geoplanet:7.6.0", "geoplanet:7.8.1", "geoplanet:7.9.0", "geoplanet:7.10.0", "geoplanet:8.0.0", "woeplanet:8.0.0"], "meta:indexed": "2020-08-20T20:15:32.561676", "meta:updated": "2020-08-22T02:54:57.767281", "woe:hierarchy": {"continent": 24865672, "country": 23424977, "town": 0, "planet": 1, "county": 12587800, "suburb": 0, "state": 2347566, "region": 0, "localadmin": 0}, "woe:timezone_id": 56043648, "woe:hash": "dr40uft75df4", "woe:centroid": [-75.721397, 39.521099], "geom:latitude": 39.521099, "geom:longitude": -75.721397, "geom:hash": "dr40uft75df4", "woe:latitude": 39.521099, "geom:centroid": [-75.721397, 39.521099], "woe:longitude": -75.721397, "woe:repo": "woeplanet-airport-us"}, "geometry": {"coordinates": [-75.721397, 39.521099], "type": "Point"}}