{"type": "Feature", "id": 12521036, "properties": {"woe:id": 12521036, "woe:parent_id": 2454673, "woe:name": "Moultonboro Airport", "woe:placetype": 14, "woe:placetype_name": "Airport", "woe:lang": "ENG", "iso:country": "US", "meta:provider": ["geoplanet:7.3.1", "geoplanet:7.3.2", "geoplanet:7.4.0", "geoplanet:7.4.1", "geoplanet:7.5.1", "geoplanet:7.5.2", "geoplanet:7.6.0", "geoplanet:7.8.1", "geoplanet:7.9.0", "geoplanet:7.10.0", "geoplanet:8.0.0", "woeplanet:8.0.0"], "meta:indexed": "2020-08-20T20:15:34.517067", "woe:alias_ENG_V": ["5m3", "Moultonborough Airport"], "meta:updated": "2020-08-22T02:54:58.123800", "woe:hierarchy": {"continent": 24865672, "country": 23424977, "town": 0, "planet": 1, "county": 12589249, "suburb": 0, "state": 2347588, "region": 0, "localadmin": 0}, "woe:timezone_id": 56043648, "woe:hash": "drv0zxcbhh71", "woe:centroid": [-71.386581, 43.768181], "geom:latitude": 43.768181, "geom:longitude": -71.386581, "geom:hash": "drv0zxcbhh71", "woe:latitude": 43.768181, "geom:centroid": [-71.386581, 43.768181], "woe:longitude": -71.386581, "woe:repo": "woeplanet-airport-us"}, "geometry": {"coordinates": [-71.386581, 43.768181], "type": "Point"}}