{"type": "Feature", "id": 29387881, "properties": {"woe:id": 29387881, "woe:parent_id": 2386592, "woe:name": "Craigmont Municipal Airport", "woe:placetype": 14, "woe:placetype_name": "Airport", "woe:lang": "ENG", "iso:country": "US", "meta:provider": ["geoplanet:7.3.1", "geoplanet:7.3.2", "geoplanet:7.4.0", "geoplanet:7.4.1", "geoplanet:7.5.1", "geoplanet:7.5.2", "geoplanet:7.6.0", "geoplanet:7.8.1", "geoplanet:7.9.0", "geoplanet:7.10.0", "geoplanet:8.0.0", "woeplanet:8.0.0"], "meta:indexed": "2020-08-20T20:15:35.421566", "woe:alias_ENG_V": ["S89", "Craigmont Muni Airport"], "meta:updated": "2020-08-22T02:54:59.791439", "woe:hierarchy": {"continent": 24865672, "country": 23424977, "town": 0, "planet": 1, "county": 12588064, "suburb": 0, "state": 2347571, "region": 0, "localadmin": 0}, "woe:timezone_id": 56043663, "woe:hash": "c2jpjddspzf0", "woe:centroid": [-116.473282, 46.24493], "geom:latitude": 46.24493, "geom:longitude": -116.473282, "geom:hash": "c2jpjddspzf0", "woe:latitude": 46.24493, "geom:centroid": [-116.473282, 46.24493], "woe:longitude": -116.473282, "woe:repo": "woeplanet-airport-us"}, "geometry": {"coordinates": [-116.473282, 46.24493], "type": "Point"}}