{"type": "Feature", "id": 12518638, "properties": {"woe:id": 12518638, "woe:parent_id": 2361763, "woe:name": "Antrim County Airport", "woe:placetype": 14, "woe:placetype_name": "Airport", "woe:lang": "ENG", "iso:country": "US", "meta:provider": ["geoplanet:7.3.1", "geoplanet:7.3.2", "geoplanet:7.4.0", "geoplanet:7.4.1", "geoplanet:7.5.1", "geoplanet:7.5.2", "geoplanet:7.6.0", "geoplanet:7.8.1", "geoplanet:7.9.0", "geoplanet:7.10.0", "geoplanet:8.0.0", "woeplanet:8.0.0"], "meta:indexed": "2020-08-20T20:15:33.151981", "woe:alias_ENG_V": ["ACB Airport", "Antrim Airport", "ACB"], "meta:updated": "2020-08-22T02:54:58.544724", "woe:hierarchy": {"continent": 24865672, "country": 23424977, "town": 0, "planet": 1, "county": 12588718, "suburb": 0, "state": 2347581, "region": 0, "localadmin": 0}, "woe:timezone_id": 56043658, "woe:hash": "dpgrvmh5p8su", "woe:centroid": [-85.193153, 44.984039], "geom:latitude": 44.984039, "geom:longitude": -85.193153, "geom:hash": "dpgrvmh5p8su", "woe:latitude": 44.984039, "geom:centroid": [-85.193153, 44.984039], "woe:longitude": -85.193153, "woe:repo": "woeplanet-airport-us"}, "geometry": {"coordinates": [-85.193153, 44.984039], "type": "Point"}}