{"type": "Feature", "id": 29388365, "geometry": {"type": "Point", "coordinates": [-78.504272, 40.0811]}, "properties": {"woe:id": 29388365, "woe:parent_id": 2361181, "woe:name": "Bedford County Airport", "woe:placetype": 14, "woe:placetype_name": "Airport", "woe:lang": "ENG", "iso:country": "US", "meta:provider": ["geoplanet:7.3.1", "geoplanet:7.3.2", "geoplanet:7.4.0", "geoplanet:7.4.1", "geoplanet:7.5.1", "geoplanet:7.5.2", "geoplanet:7.6.0", "geoplanet:7.8.1", "geoplanet:7.9.0", "geoplanet:7.10.0", "geoplanet:8.0.0", "woeplanet:8.0.0"], "meta:indexed": "2020-08-20T20:15:35.806655", "woe:alias_ENG_V": ["Hmz"], "meta:updated": "2020-10-14T11:44:06.923190", "woe:hierarchy": {"continent": 24865672, "country": 23424977, "town": 0, "planet": 1, "county": 12589732, "suburb": 0, "state": 2347597, "region": 0, "localadmin": 0}, "woe:timezone_id": 56043648, "woe:hash": "dr0hj8dcmfs4", "woe:centroid": [-78.504272, 40.0811], "geom:latitude": 40.0811, "geom:longitude": -78.504272, "geom:hash": "dr0hj8dcmfs4", "woe:latitude": 40.0811, "geom:centroid": [-78.504272, 40.0811], "woe:longitude": -78.504272, "woe:repo": "woeplanet-airport-us", "geom:area": 0.0, "woe:scale": 19}}