{"type": "Feature", "id": 12520862, "properties": {"woe:id": 12520862, "woe:parent_id": 2428173, "woe:name": "Mckellar Sipes Regional Airport", "woe:placetype": 14, "woe:placetype_name": "Airport", "woe:lang": "ENG", "iso:country": "US", "meta:provider": ["geoplanet:7.3.1", "geoplanet:7.3.2", "geoplanet:7.4.0", "geoplanet:7.4.1", "geoplanet:7.5.1", "geoplanet:7.5.2", "geoplanet:7.6.0", "geoplanet:7.8.1", "geoplanet:7.9.0", "geoplanet:7.10.0", "geoplanet:8.0.0", "woeplanet:8.0.0"], "meta:indexed": "2020-08-20T20:15:34.420580", "woe:alias_ENG_V": ["Mckellar-Sipes Regional Airport", "Mckellar Sipes Regional", "MKL", "MKL Airport", "Mckellar Sipes", "Mckellar Sipes Airport", "Mc Kellar-sipes Rgnl Airport", "Mc Kellar-sipes Regional Airport"], "meta:updated": "2020-08-22T02:54:59.099611", "woe:hierarchy": {"continent": 24865672, "country": 23424977, "town": 0, "planet": 1, "county": 12589966, "suburb": 0, "state": 2347601, "region": 0, "localadmin": 0}, "woe:timezone_id": 56043661, "woe:hash": "dn2f893081j9", "woe:centroid": [-88.921959, 35.602661], "geom:latitude": 35.602661, "geom:longitude": -88.921959, "geom:hash": "dn2f893081j9", "woe:latitude": 35.602661, "geom:centroid": [-88.921959, 35.602661], "woe:longitude": -88.921959, "woe:repo": "woeplanet-airport-us"}, "geometry": {"coordinates": [-88.921959, 35.602661], "type": "Point"}}