{"type": "Feature", "id": 12519263, "properties": {"woe:id": 12519263, "woe:parent_id": 2480168, "woe:name": "Codell Airport", "woe:placetype": 14, "woe:placetype_name": "Airport", "woe:lang": "ENG", "iso:country": "US", "meta:provider": ["geoplanet:7.3.1", "geoplanet:7.3.2", "geoplanet:7.4.0", "geoplanet:7.4.1", "geoplanet:7.5.1", "geoplanet:7.5.2", "geoplanet:7.6.0", "geoplanet:7.8.1", "geoplanet:7.9.0", "geoplanet:7.10.0", "geoplanet:8.0.0", "woeplanet:8.0.0"], "meta:indexed": "2020-08-20T20:15:33.550288", "meta:updated": "2020-08-22T02:54:58.692053", "woe:hierarchy": {"continent": 24865672, "country": 23424977, "town": 0, "planet": 1, "county": 12588500, "suburb": 0, "state": 2347576, "region": 0, "localadmin": 0}, "woe:timezone_id": 56043647, "woe:hash": "dnu079ee962n", "woe:centroid": [-84.216331, 38.021549], "geom:latitude": 38.021549, "geom:longitude": -84.216331, "geom:hash": "dnu079ee962n", "woe:latitude": 38.021549, "geom:centroid": [-84.216331, 38.021549], "woe:longitude": -84.216331, "woe:repo": "woeplanet-airport-us"}, "geometry": {"coordinates": [-84.216331, 38.021549], "type": "Point"}}