{"type": "Feature", "id": 12521945, "properties": {"woe:id": 12521945, "woe:parent_id": 2498261, "woe:name": "Springfield Municipal Airport", "woe:placetype": 14, "woe:placetype_name": "Airport", "woe:lang": "ENG", "iso:country": "US", "meta:provider": ["geoplanet:7.3.1", "geoplanet:7.3.2", "geoplanet:7.4.0", "geoplanet:7.4.1", "geoplanet:7.5.1", "geoplanet:7.5.2", "geoplanet:7.6.0", "geoplanet:7.8.1", "geoplanet:7.9.0", "geoplanet:7.10.0", "geoplanet:8.0.0", "woeplanet:8.0.0"], "meta:indexed": "2020-08-20T20:15:34.982869", "woe:alias_ENG_V": ["8v7", "Springfield Muni Airport"], "meta:updated": "2020-08-22T02:54:59.373989", "woe:hierarchy": {"continent": 24865672, "country": 23424977, "town": 0, "planet": 1, "county": 12587732, "suburb": 0, "state": 2347564, "region": 0, "localadmin": 0}, "woe:timezone_id": 56043665, "woe:hash": "9wxj0u43yg8m", "woe:centroid": [-102.619911, 37.463699], "geom:latitude": 37.463699, "geom:longitude": -102.619911, "geom:hash": "9wxj0u43yg8m", "woe:latitude": 37.463699, "geom:centroid": [-102.619911, 37.463699], "woe:longitude": -102.619911, "woe:repo": "woeplanet-airport-us"}, "geometry": {"coordinates": [-102.619911, 37.463699], "type": "Point"}}