{"type": "Feature", "id": 12518872, "geometry": {"type": "Point", "coordinates": [-119.812271, 45.817871]}, "properties": {"woe:id": 12518872, "woe:parent_id": 2366150, "woe:name": "Boardman Airport", "woe:placetype": 14, "woe:placetype_name": "Airport", "woe:lang": "ENG", "iso:country": "US", "meta:provider": ["geoplanet:7.3.1", "geoplanet:7.3.2", "geoplanet:7.4.0", "geoplanet:7.4.1", "geoplanet:7.5.1", "geoplanet:7.5.2", "geoplanet:7.6.0", "geoplanet:7.8.1", "geoplanet:7.9.0", "geoplanet:7.10.0", "geoplanet:8.0.0", "woeplanet:8.0.0"], "meta:indexed": "2020-08-20T20:15:31.770294", "woe:alias_ENG_V": ["M50"], "meta:updated": "2020-10-14T11:44:08.465462", "woe:hierarchy": {"continent": 24865672, "country": 23424977, "town": 0, "planet": 1, "county": 12589716, "suburb": 0, "state": 2347596, "region": 0, "localadmin": 0}, "woe:timezone_id": 56043663, "woe:hash": "c24u9sgk7wpw", "woe:centroid": [-119.812271, 45.817871], "geom:latitude": 45.817871, "geom:longitude": -119.812271, "geom:hash": "c24u9sgk7wpw", "woe:latitude": 45.817871, "geom:centroid": [-119.812271, 45.817871], "woe:longitude": -119.812271, "woe:repo": "woeplanet-airport-us", "geom:area": 0.0, "woe:scale": 19}}