{"type": "Feature", "id": 12519404, "geometry": {"type": "Point", "coordinates": [-84.872101, 34.721321]}, "properties": {"woe:id": 12519404, "woe:parent_id": 2389073, "woe:name": "Dalton Municipal Airport", "woe:placetype": 14, "woe:placetype_name": "Airport", "woe:lang": "ENG", "iso:country": "US", "meta:provider": ["geoplanet:7.3.1", "geoplanet:7.3.2", "geoplanet:7.4.0", "geoplanet:7.4.1", "geoplanet:7.5.1", "geoplanet:7.5.2", "geoplanet:7.6.0", "geoplanet:7.8.1", "geoplanet:7.9.0", "geoplanet:7.10.0", "geoplanet:8.0.0", "woeplanet:8.0.0"], "meta:indexed": "2020-08-20T20:15:33.640655", "woe:alias_ENG_V": ["DNN Airport", "Dalton Airport", "Dalton Municipal", "DNN", "Dalton Muni Airport"], "meta:updated": "2020-10-14T11:44:08.589702", "woe:hierarchy": {"continent": 24865672, "country": 23424977, "town": 0, "planet": 1, "county": 12588024, "suburb": 0, "state": 2347569, "region": 0, "localadmin": 0}, "woe:timezone_id": 56043648, "woe:hash": "dn5ts8y42eqe", "woe:centroid": [-84.872101, 34.721321], "geom:latitude": 34.721321, "geom:longitude": -84.872101, "geom:hash": "dn5ts8y42eqe", "woe:latitude": 34.721321, "geom:centroid": [-84.872101, 34.721321], "woe:longitude": -84.872101, "woe:repo": "woeplanet-airport-us", "geom:area": 0.0, "woe:scale": 19}}