{"type": "Feature", "id": 12519654, "geometry": {"type": "Point", "coordinates": [-79.853943, 42.044498]}, "properties": {"woe:id": 12519654, "woe:parent_id": 28744815, "woe:name": "Erie County Airport", "woe:placetype": 14, "woe:placetype_name": "Airport", "woe:lang": "ENG", "iso:country": "US", "meta:provider": ["geoplanet:7.3.1", "geoplanet:7.3.2", "geoplanet:7.4.0", "geoplanet:7.4.1", "geoplanet:7.5.1", "geoplanet:7.5.2", "geoplanet:7.6.0", "geoplanet:7.8.1", "geoplanet:7.9.0", "geoplanet:7.10.0", "geoplanet:8.0.0", "woeplanet:8.0.0"], "meta:indexed": "2020-08-20T20:15:31.962167", "meta:updated": "2020-10-14T11:44:09.035315", "woe:hierarchy": {"continent": 24865672, "country": 23424977, "town": 0, "planet": 1, "county": 12589752, "suburb": 0, "state": 2347597, "region": 0, "localadmin": 0}, "woe:timezone_id": 56043648, "woe:hash": "dprpnvunuq2r", "woe:centroid": [-79.853943, 42.044498], "geom:latitude": 42.044498, "geom:longitude": -79.853943, "geom:hash": "dprpnvunuq2r", "woe:latitude": 42.044498, "geom:centroid": [-79.853943, 42.044498], "woe:longitude": -79.853943, "woe:repo": "woeplanet-airport-us", "geom:area": 0.0, "woe:scale": 19}}