{"type": "Feature", "id": 29388541, "geometry": {"type": "Point", "coordinates": [-84.412857, 31.7383]}, "properties": {"woe:id": 29388541, "woe:parent_id": 2389780, "woe:name": "Dawson Municipal Airport", "woe:placetype": 14, "woe:placetype_name": "Airport", "woe:lang": "ENG", "iso:country": "US", "meta:provider": ["geoplanet:7.3.1", "geoplanet:7.3.2", "geoplanet:7.4.0", "geoplanet:7.4.1", "geoplanet:7.5.1", "geoplanet:7.5.2", "geoplanet:7.6.0", "geoplanet:7.8.1", "geoplanet:7.9.0", "geoplanet:7.10.0", "geoplanet:8.0.0", "woeplanet:8.0.0"], "meta:indexed": "2020-08-20T20:15:35.924313", "woe:alias_ENG_V": ["16j", "Dawson Muni Airport"], "meta:updated": "2020-10-14T11:44:06.790288", "woe:hierarchy": {"continent": 24865672, "country": 23424977, "town": 0, "planet": 1, "county": 12588004, "suburb": 0, "state": 2347569, "region": 0, "localadmin": 0}, "woe:timezone_id": 56043648, "woe:hash": "djeux1u2vzgy", "woe:centroid": [-84.412857, 31.7383], "geom:latitude": 31.7383, "geom:longitude": -84.412857, "geom:hash": "djeux1u2vzgy", "woe:latitude": 31.7383, "geom:centroid": [-84.412857, 31.7383], "woe:longitude": -84.412857, "woe:repo": "woeplanet-airport-us", "geom:area": 0.0, "woe:scale": 19}}