{"type": "Feature", "id": 12519706, "geometry": {"type": "Point", "coordinates": [-91.480614, 30.71858]}, "properties": {"woe:id": 12519706, "woe:parent_id": 2370034, "woe:name": "False River Air Park", "woe:placetype": 14, "woe:placetype_name": "Airport", "woe:lang": "ENG", "iso:country": "US", "meta:provider": ["geoplanet:7.3.1", "geoplanet:7.3.2", "geoplanet:7.4.0", "geoplanet:7.4.1", "geoplanet:7.5.1", "geoplanet:7.5.2", "geoplanet:7.6.0", "geoplanet:7.8.1", "geoplanet:7.9.0", "geoplanet:7.10.0", "geoplanet:8.0.0", "woeplanet:8.0.0"], "meta:indexed": "2020-08-20T20:15:33.798960", "woe:alias_ENG_V": ["False River Regional Airport", "Hzr", "False River Rgnl Airport"], "meta:updated": "2020-10-14T11:44:09.595646", "woe:hierarchy": {"continent": 24865672, "country": 23424977, "town": 0, "planet": 1, "county": 12588634, "suburb": 0, "state": 2347577, "region": 0, "localadmin": 0}, "woe:timezone_id": 56043661, "woe:hash": "9vqyy21uenq5", "woe:centroid": [-91.480614, 30.71858], "geom:latitude": 30.71858, "geom:longitude": -91.480614, "geom:hash": "9vqyy21uenq5", "woe:latitude": 30.71858, "geom:centroid": [-91.480614, 30.71858], "woe:longitude": -91.480614, "woe:repo": "woeplanet-airport-us", "geom:area": 0.0, "woe:scale": 19}}