{"type": "Feature", "id": 12519126, "properties": {"woe:id": 12519126, "woe:parent_id": 2377849, "woe:name": "Challis Airport", "woe:placetype": 14, "woe:placetype_name": "Airport", "woe:lang": "ENG", "iso:country": "US", "meta:provider": ["geoplanet:7.3.1", "geoplanet:7.3.2", "geoplanet:7.4.0", "geoplanet:7.4.1", "geoplanet:7.5.1", "geoplanet:7.5.2", "geoplanet:7.6.0", "geoplanet:7.8.1", "geoplanet:7.9.0", "geoplanet:7.10.0", "geoplanet:8.0.0", "woeplanet:8.0.0"], "meta:indexed": "2020-08-20T20:15:33.465463", "woe:alias_ENG_V": ["Llj", "CHL Airport", "CHL"], "meta:updated": "2020-08-22T02:54:58.658402", "woe:hierarchy": {"continent": 24865672, "country": 23424977, "town": 0, "planet": 1, "county": 12588052, "suburb": 0, "state": 2347571, "region": 0, "localadmin": 0}, "woe:timezone_id": 56043662, "woe:hash": "9ryv2bqyrcfm", "woe:centroid": [-114.215248, 44.519058], "geom:latitude": 44.519058, "geom:longitude": -114.215248, "geom:hash": "9ryv2bqyrcfm", "woe:latitude": 44.519058, "geom:centroid": [-114.215248, 44.519058], "woe:longitude": -114.215248, "woe:repo": "woeplanet-airport-us"}, "geometry": {"coordinates": [-114.215248, 44.519058], "type": "Point"}}