{"type": "Feature", "id": 12521331, "geometry": {"type": "Point", "coordinates": [-76.857498, 40.814671]}, "properties": {"woe:id": 12521331, "woe:parent_id": 28340166, "woe:name": "Penn Valley Airport", "woe:placetype": 14, "woe:placetype_name": "Airport", "woe:lang": "ENG", "iso:country": "US", "meta:provider": ["geoplanet:7.3.1", "geoplanet:7.3.2", "geoplanet:7.4.0", "geoplanet:7.4.1", "geoplanet:7.5.1", "geoplanet:7.5.2", "geoplanet:7.6.0", "geoplanet:7.8.1", "geoplanet:7.9.0", "geoplanet:7.10.0", "geoplanet:8.0.0", "woeplanet:8.0.0"], "meta:indexed": "2020-08-20T20:15:34.681438", "woe:alias_ENG_V": ["SEG Airport", "SEG"], "meta:updated": "2020-10-14T11:44:08.776307", "woe:hierarchy": {"continent": 24865672, "country": 23424977, "town": 0, "planet": 1, "county": 12589782, "suburb": 0, "state": 2347597, "region": 0, "localadmin": 0}, "woe:timezone_id": 56043648, "woe:hash": "dr325n44dqpu", "woe:centroid": [-76.857498, 40.814671], "geom:latitude": 40.814671, "geom:longitude": -76.857498, "geom:hash": "dr325n44dqpu", "woe:latitude": 40.814671, "geom:centroid": [-76.857498, 40.814671], "woe:longitude": -76.857498, "woe:repo": "woeplanet-airport-us", "geom:area": 0.0, "woe:scale": 19}}