{"type": "Feature", "id": 12519944, "properties": {"woe:id": 12519944, "woe:parent_id": 2380583, "woe:name": "Gragg Wade Field Airport", "woe:placetype": 14, "woe:placetype_name": "Airport", "woe:lang": "ENG", "iso:country": "US", "meta:provider": ["geoplanet:7.3.1", "geoplanet:7.3.2", "geoplanet:7.4.0", "geoplanet:7.4.1", "geoplanet:7.5.1", "geoplanet:7.5.2", "geoplanet:7.6.0", "geoplanet:7.8.1", "geoplanet:7.9.0", "geoplanet:7.10.0", "geoplanet:8.0.0", "woeplanet:8.0.0"], "meta:indexed": "2020-08-20T20:15:33.927473", "woe:alias_ENG_V": ["Gragg Field", "02a", "Chilton County Airport"], "meta:updated": "2020-08-22T02:54:58.868369", "woe:hierarchy": {"continent": 24865672, "country": 23424977, "town": 0, "planet": 1, "county": 12587497, "suburb": 0, "state": 2347559, "region": 0, "localadmin": 0}, "woe:timezone_id": 56043661, "woe:hash": "djf6vhu2dwj2", "woe:centroid": [-86.61026, 32.853359], "geom:latitude": 32.853359, "geom:longitude": -86.61026, "geom:hash": "djf6vhu2dwj2", "woe:latitude": 32.853359, "geom:centroid": [-86.61026, 32.853359], "woe:longitude": -86.61026, "woe:repo": "woeplanet-airport-us"}, "geometry": {"coordinates": [-86.61026, 32.853359], "type": "Point"}}