{"type": "Feature", "id": 12520203, "geometry": {"type": "Point", "coordinates": [-121.402206, 36.889111]}, "properties": {"woe:id": 12520203, "woe:parent_id": 2423203, "woe:name": "Hollister Municipal Airport", "woe:placetype": 14, "woe:placetype_name": "Airport", "woe:lang": "ENG", "iso:country": "US", "meta:provider": ["geoplanet:7.3.1", "geoplanet:7.3.2", "geoplanet:7.4.0", "geoplanet:7.4.1", "geoplanet:7.5.1", "geoplanet:7.5.2", "geoplanet:7.6.0", "geoplanet:7.8.1", "geoplanet:7.9.0", "geoplanet:7.10.0", "geoplanet:8.0.0", "woeplanet:8.0.0"], "meta:indexed": "2020-08-20T20:15:34.075025", "woe:alias_ENG_V": ["Hli", "Hollister Muni Airport", "CVH"], "meta:updated": "2020-10-14T11:44:08.155770", "woe:hierarchy": {"continent": 24865672, "country": 23424977, "town": 0, "planet": 1, "county": 12587704, "suburb": 0, "state": 2347563, "region": 0, "localadmin": 0}, "woe:timezone_id": 56043663, "woe:hash": "9q99v7mwesdn", "woe:centroid": [-121.402206, 36.889111], "geom:latitude": 36.889111, "geom:longitude": -121.402206, "geom:hash": "9q99v7mwesdn", "woe:latitude": 36.889111, "geom:centroid": [-121.402206, 36.889111], "woe:longitude": -121.402206, "woe:repo": "woeplanet-airport-us", "geom:area": 0.0, "woe:scale": 19}}