{"type": "Feature", "id": 12518701, "geometry": {"type": "Point", "coordinates": [-104.653961, 39.737541]}, "properties": {"woe:id": 12518701, "woe:parent_id": 55806601, "woe:name": "Aurora Airport", "woe:placetype": 14, "woe:placetype_name": "Airport", "woe:lang": "ENG", "iso:country": "US", "meta:provider": ["geoplanet:7.3.1", "geoplanet:7.3.2", "geoplanet:7.4.0", "geoplanet:7.4.1", "geoplanet:7.5.1", "geoplanet:7.5.2", "geoplanet:7.6.0", "geoplanet:7.8.1", "geoplanet:7.9.0", "geoplanet:7.10.0", "geoplanet:8.0.0", "woeplanet:8.0.0"], "meta:indexed": "2020-08-20T20:15:31.730693", "woe:alias_ENG_V": ["Aurora Airpark"], "meta:updated": "2020-10-14T11:44:08.927950", "woe:hierarchy": {"continent": 24865672, "country": 23424977, "town": 0, "planet": 1, "county": 12587730, "suburb": 0, "state": 2347564, "region": 0, "localadmin": 0}, "woe:timezone_id": 56043665, "woe:hash": "9xjd49crcyw9", "woe:centroid": [-104.653961, 39.737541], "geom:latitude": 39.737541, "geom:longitude": -104.653961, "geom:hash": "9xjd49crcyw9", "woe:latitude": 39.737541, "geom:centroid": [-104.653961, 39.737541], "woe:longitude": -104.653961, "woe:repo": "woeplanet-airport-us", "geom:area": 0.0, "woe:scale": 19}}