{"type": "Feature", "id": 12519395, "geometry": {"type": "Point", "coordinates": [-84.29113, 38.369049]}, "properties": {"woe:id": 12519395, "woe:parent_id": 2388604, "woe:name": "Cynthiana Harrison County Airport", "woe:placetype": 14, "woe:placetype_name": "Airport", "woe:lang": "ENG", "iso:country": "US", "meta:provider": ["geoplanet:7.3.1", "geoplanet:7.3.2", "geoplanet:7.4.0", "geoplanet:7.4.1", "geoplanet:7.5.1", "geoplanet:7.5.2", "geoplanet:7.6.0", "geoplanet:7.8.1", "geoplanet:7.9.0", "geoplanet:7.10.0", "geoplanet:8.0.0", "woeplanet:8.0.0"], "meta:indexed": "2020-08-20T20:15:33.638217", "woe:alias_ENG_V": ["Cynthiana-Harrison County Airport", "0i8"], "meta:updated": "2020-10-14T11:44:09.881828", "woe:hierarchy": {"continent": 24865672, "country": 23424977, "town": 0, "planet": 1, "county": 12588524, "suburb": 0, "state": 2347576, "region": 0, "localadmin": 0}, "woe:timezone_id": 56043647, "woe:hash": "dnu43bv5fm4h", "woe:centroid": [-84.29113, 38.369049], "geom:latitude": 38.369049, "geom:longitude": -84.29113, "geom:hash": "dnu43bv5fm4h", "woe:latitude": 38.369049, "geom:centroid": [-84.29113, 38.369049], "woe:longitude": -84.29113, "woe:repo": "woeplanet-airport-us", "geom:area": 0.0, "woe:scale": 19}}