{"type": "Feature", "id": 12521260, "properties": {"woe:id": 12521260, "woe:parent_id": 2358056, "woe:name": "Ottawa Municipal Airport", "woe:placetype": 14, "woe:placetype_name": "Airport", "woe:lang": "ENG", "iso:country": "US", "meta:provider": ["geoplanet:7.3.1", "geoplanet:7.3.2", "geoplanet:7.4.0", "geoplanet:7.4.1", "geoplanet:7.5.1", "geoplanet:7.5.2", "geoplanet:7.6.0", "geoplanet:7.8.1", "geoplanet:7.9.0", "geoplanet:7.10.0", "geoplanet:8.0.0", "woeplanet:8.0.0"], "meta:indexed": "2020-08-20T20:15:34.639878", "woe:alias_ENG_V": ["OWI Airport", "OWI", "Ottawa Muni Airport"], "meta:updated": "2020-08-22T02:54:59.203557", "woe:hierarchy": {"continent": 24865672, "country": 23424977, "town": 0, "planet": 1, "county": 12588400, "suburb": 0, "state": 2347575, "region": 0, "localadmin": 0}, "woe:timezone_id": 56043661, "woe:hash": "9yu7283kuvcf", "woe:centroid": [-95.249542, 38.542259], "geom:latitude": 38.542259, "geom:longitude": -95.249542, "geom:hash": "9yu7283kuvcf", "woe:latitude": 38.542259, "geom:centroid": [-95.249542, 38.542259], "woe:longitude": -95.249542, "woe:repo": "woeplanet-airport-us"}, "geometry": {"coordinates": [-95.249542, 38.542259], "type": "Point"}}