{"type": "Feature", "id": 12521832, "properties": {"woe:id": 12521832, "woe:parent_id": 2474258, "woe:name": "Sher Wood Airport", "woe:placetype": 14, "woe:placetype_name": "Airport", "woe:lang": "ENG", "iso:country": "US", "meta:provider": ["geoplanet:7.3.1", "geoplanet:7.3.2", "geoplanet:7.4.0", "geoplanet:7.4.1", "geoplanet:7.5.1", "geoplanet:7.5.2", "geoplanet:7.6.0", "geoplanet:7.8.1", "geoplanet:7.9.0", "geoplanet:7.10.0", "geoplanet:8.0.0", "woeplanet:8.0.0"], "meta:indexed": "2020-08-20T20:15:34.924319", "woe:alias_ENG_V": ["PWD", "PWD Airport", "Sher-Wood Airport", "Sherwood Airport", "Sher Wood"], "meta:updated": "2020-08-22T02:54:58.156523", "woe:hierarchy": {"continent": 24865672, "country": 23424977, "town": 0, "planet": 1, "county": 12589126, "suburb": 0, "state": 2347585, "region": 0, "localadmin": 0}, "woe:timezone_id": 56043665, "woe:hash": "c8ttt3t7r68y", "woe:centroid": [-104.52739, 48.788109], "geom:latitude": 48.788109, "geom:longitude": -104.52739, "geom:hash": "c8ttt3t7r68y", "woe:latitude": 48.788109, "geom:centroid": [-104.52739, 48.788109], "woe:longitude": -104.52739, "woe:repo": "woeplanet-airport-us"}, "geometry": {"coordinates": [-104.52739, 48.788109], "type": "Point"}}