{"type": "Feature", "id": 12519248, "geometry": {"type": "Point", "coordinates": [-88.73214, 44.618969]}, "properties": {"woe:id": 12519248, "woe:parent_id": 2381833, "woe:name": "Clintonville Municipal Airport", "woe:placetype": 14, "woe:placetype_name": "Airport", "woe:lang": "ENG", "iso:country": "US", "meta:provider": ["geoplanet:7.3.1", "geoplanet:7.3.2", "geoplanet:7.4.0", "geoplanet:7.4.1", "geoplanet:7.5.1", "geoplanet:7.5.2", "geoplanet:7.6.0", "geoplanet:7.8.1", "geoplanet:7.9.0", "geoplanet:7.10.0", "geoplanet:8.0.0", "woeplanet:8.0.0"], "meta:indexed": "2020-08-20T20:15:33.541764", "woe:alias_ENG_V": ["Clintonville Municipal", "CLI", "CLI Airport", "Clintonville Airport", "Clintonville Muni Airport"], "meta:updated": "2020-10-14T11:44:09.930149", "woe:hierarchy": {"continent": 24865672, "country": 23424977, "town": 0, "planet": 1, "county": 12590602, "suburb": 0, "state": 2347608, "region": 0, "localadmin": 0}, "woe:timezone_id": 56043661, "woe:hash": "dpbvufehr68v", "woe:centroid": [-88.73214, 44.618969], "geom:latitude": 44.618969, "geom:longitude": -88.73214, "geom:hash": "dpbvufehr68v", "woe:latitude": 44.618969, "geom:centroid": [-88.73214, 44.618969], "woe:longitude": -88.73214, "woe:repo": "woeplanet-airport-us", "geom:area": 0.0, "woe:scale": 19}}