{"type": "Feature", "id": 12520400, "properties": {"woe:id": 12520400, "woe:parent_id": 2429939, "woe:name": "Joplin Regional Airport", "woe:placetype": 14, "woe:placetype_name": "Airport", "woe:lang": "ENG", "iso:country": "US", "meta:provider": ["geoplanet:7.3.1", "geoplanet:7.3.2", "geoplanet:7.4.0", "geoplanet:7.4.1", "geoplanet:7.5.1", "geoplanet:7.5.2", "geoplanet:7.6.0", "geoplanet:7.8.1", "geoplanet:7.9.0", "geoplanet:7.10.0", "geoplanet:8.0.0", "woeplanet:8.0.0"], "meta:indexed": "2020-08-20T20:15:34.179666", "woe:alias_ENG_V": ["Joplin Regional", "JLN", "JLN Airport", "Joplin Airport", "Joplin Rgnl Airport"], "meta:updated": "2020-08-22T02:54:58.987421", "woe:hierarchy": {"continent": 24865672, "country": 23424977, "town": 0, "planet": 1, "county": 12589014, "suburb": 0, "state": 2347584, "region": 0, "localadmin": 0}, "woe:timezone_id": 56043661, "woe:hash": "9ysg3s3fsq8t", "woe:centroid": [-94.501808, 37.1576], "geom:latitude": 37.1576, "geom:longitude": -94.501808, "geom:hash": "9ysg3s3fsq8t", "woe:latitude": 37.1576, "geom:centroid": [-94.501808, 37.1576], "woe:longitude": -94.501808, "woe:repo": "woeplanet-airport-us"}, "geometry": {"coordinates": [-94.501808, 37.1576], "type": "Point"}}