{"type": "Feature", "id": 12522218, "geometry": {"type": "Point", "coordinates": [-86.24472, 35.373821]}, "properties": {"woe:id": 12522218, "woe:parent_id": 2508513, "woe:name": "Tullahoma Regional Airport-William Northern Field", "woe:placetype": 14, "woe:placetype_name": "Airport", "woe:lang": "ENG", "iso:country": "US", "meta:provider": ["geoplanet:7.3.1", "geoplanet:7.3.2", "geoplanet:7.4.0", "geoplanet:7.4.1", "geoplanet:7.5.1", "geoplanet:7.5.2", "geoplanet:7.6.0", "geoplanet:7.8.1", "geoplanet:7.9.0", "geoplanet:7.10.0", "geoplanet:8.0.0", "woeplanet:8.0.0"], "meta:indexed": "2020-08-20T20:15:32.618336", "woe:alias_ENG_V": ["Tullahoma-William Northern", "Tullahoma-William Northern Field", "THA", "THA Airport", "Tullahoma Municipal Airport", "Tullahoma Airport-William Northern", "Tullahoma Airport-William Northern Field", "Tullahoma Regional Airport-William Northern", "Tullahoma Regional-William Northern", "Tullahoma Regional-William Northern Field", "Tullahoma Rgnl Arpt - Wm Northern Field", "Tullahoma Regional Arpt - Wm Northern Field"], "meta:updated": "2020-10-14T11:44:09.364312", "woe:hierarchy": {"continent": 24865672, "country": 23424977, "town": 0, "planet": 1, "county": 12589927, "suburb": 0, "state": 2347601, "region": 0, "localadmin": 0}, "woe:hash": "dn69jrwe2q5t", "woe:centroid": [-86.24472, 35.373821], "geom:latitude": 35.373821, "geom:longitude": -86.24472, "geom:hash": "dn69jrwe2q5t", "woe:latitude": 35.373821, "geom:centroid": [-86.24472, 35.373821], "woe:longitude": -86.24472, "woe:repo": "woeplanet-airport-us", "geom:area": 0.0, "woe:scale": 19}}