{"type": "Feature", "id": 12520348, "properties": {"woe:id": 12520348, "woe:parent_id": 2428576, "woe:name": "Jamestown Municipal Airport", "woe:placetype": 14, "woe:placetype_name": "Airport", "woe:lang": "ENG", "iso:country": "US", "meta:provider": ["geoplanet:7.3.1", "geoplanet:7.3.2", "geoplanet:7.4.0", "geoplanet:7.4.1", "geoplanet:7.5.1", "geoplanet:7.5.2", "geoplanet:7.6.0", "geoplanet:7.8.1", "geoplanet:7.9.0", "geoplanet:7.10.0", "geoplanet:8.0.0", "woeplanet:8.0.0"], "meta:indexed": "2020-08-20T20:15:34.149729", "woe:alias_ENG_V": ["JMS", "JMS Airport", "Jamestown Airport", "Jamestown Municipal", "Jamestown Regional Airport", "Jamestown Rgnl Airport"], "meta:updated": "2020-08-22T02:54:58.972504", "woe:hierarchy": {"continent": 24865672, "country": 23424977, "town": 0, "planet": 1, "county": 12589520, "suburb": 0, "state": 2347593, "region": 0, "localadmin": 0}, "woe:timezone_id": 56043661, "woe:hash": "cb3ffw263k05", "woe:centroid": [-98.678802, 46.924389], "geom:latitude": 46.924389, "geom:longitude": -98.678802, "geom:hash": "cb3ffw263k05", "woe:latitude": 46.924389, "geom:centroid": [-98.678802, 46.924389], "woe:longitude": -98.678802, "woe:repo": "woeplanet-airport-us"}, "geometry": {"coordinates": [-98.678802, 46.924389], "type": "Point"}}