{"type": "Feature", "id": 12519742, "properties": {"woe:id": 12519742, "woe:parent_id": 2395115, "woe:name": "Fletcher Field Airport", "woe:placetype": 14, "woe:placetype_name": "Airport", "woe:lang": "ENG", "iso:country": "US", "meta:provider": ["geoplanet:7.3.1", "geoplanet:7.3.2", "geoplanet:7.4.0", "geoplanet:7.4.1", "geoplanet:7.5.1", "geoplanet:7.5.2", "geoplanet:7.6.0", "geoplanet:7.8.1", "geoplanet:7.9.0", "geoplanet:7.10.0", "geoplanet:8.0.0", "woeplanet:8.0.0"], "meta:indexed": "2020-08-20T20:15:33.819171", "woe:alias_ENG_V": ["Clarksdale", "CKM Airport", "Fletcher Airport", "CKM", "Clarksdale Coahoma County Airport", "Fletcher Field"], "meta:updated": "2020-08-22T02:54:58.814827", "woe:hierarchy": {"continent": 24865672, "country": 23424977, "town": 0, "planet": 1, "county": 12588897, "suburb": 0, "state": 2347583, "region": 0, "localadmin": 0}, "woe:timezone_id": 56043661, "woe:hash": "9ypeh62hn6h9", "woe:centroid": [-90.516083, 34.290401], "geom:latitude": 34.290401, "geom:longitude": -90.516083, "geom:hash": "9ypeh62hn6h9", "woe:latitude": 34.290401, "geom:centroid": [-90.516083, 34.290401], "woe:longitude": -90.516083, "woe:repo": "woeplanet-airport-us"}, "geometry": {"coordinates": [-90.516083, 34.290401], "type": "Point"}}