{"type": "Feature", "id": 12518578, "properties": {"woe:id": 12518578, "woe:parent_id": 2495524, "woe:name": "Allen H Tigert Airport", "woe:placetype": 14, "woe:placetype_name": "Airport", "woe:lang": "ENG", "iso:country": "US", "meta:provider": ["geoplanet:7.3.1", "geoplanet:7.3.2", "geoplanet:7.4.0", "geoplanet:7.4.1", "geoplanet:7.5.1", "geoplanet:7.5.2", "geoplanet:7.6.0", "geoplanet:7.8.1", "geoplanet:7.9.0", "geoplanet:7.10.0", "geoplanet:8.0.0", "woeplanet:8.0.0"], "meta:indexed": "2020-08-20T20:15:33.115637", "woe:alias_ENG_V": ["U78"], "meta:updated": "2020-08-22T02:54:58.033310", "woe:hierarchy": {"continent": 24865672, "country": 23424977, "town": 0, "planet": 1, "county": 12588048, "suburb": 0, "state": 2347571, "region": 0, "localadmin": 0}, "woe:timezone_id": 56043662, "woe:hash": "9x8dsu6vt904", "woe:centroid": [-111.584122, 42.651249], "geom:latitude": 42.651249, "geom:longitude": -111.584122, "geom:hash": "9x8dsu6vt904", "woe:latitude": 42.651249, "geom:centroid": [-111.584122, 42.651249], "woe:longitude": -111.584122, "woe:repo": "woeplanet-airport-us"}, "geometry": {"coordinates": [-111.584122, 42.651249], "type": "Point"}}