{"type": "Feature", "id": 29388165, "properties": {"woe:id": 29388165, "woe:parent_id": 2454592, "woe:name": "Fundarosa Airport", "woe:placetype": 14, "woe:placetype_name": "Airport", "woe:lang": "ENG", "iso:country": "US", "meta:provider": ["geoplanet:7.3.1", "geoplanet:7.3.2", "geoplanet:7.4.0", "geoplanet:7.4.1", "geoplanet:7.5.1", "geoplanet:7.5.2", "geoplanet:7.6.0", "geoplanet:7.8.1", "geoplanet:7.9.0", "geoplanet:7.10.0", "geoplanet:8.0.0", "woeplanet:8.0.0"], "meta:indexed": "2020-08-20T20:15:35.676744", "meta:updated": "2020-08-22T02:54:58.223908", "woe:alias_ENG_V": ["Fundarosa Field"], "woe:hierarchy": {"continent": 24865672, "country": 23424977, "town": 0, "planet": 1, "county": 12588913, "suburb": 0, "state": 2347583, "region": 0, "localadmin": 0}, "woe:timezone_id": 56043661, "woe:hash": "dj3j6es3uvyy", "woe:centroid": [-88.477837, 30.47366], "geom:latitude": 30.47366, "geom:longitude": -88.477837, "geom:hash": "dj3j6es3uvyy", "woe:latitude": 30.47366, "geom:centroid": [-88.477837, 30.47366], "woe:longitude": -88.477837, "woe:repo": "woeplanet-airport-us"}, "geometry": {"coordinates": [-88.477837, 30.47366], "type": "Point"}}