{"type": "Feature", "id": 29388317, "geometry": {"type": "Point", "coordinates": [-80.768341, 41.752831]}, "properties": {"woe:id": 29388317, "woe:parent_id": 2428840, "woe:name": "Jefferson Airport", "woe:placetype": 14, "woe:placetype_name": "Airport", "woe:lang": "ENG", "iso:country": "US", "meta:provider": ["geoplanet:7.3.1", "geoplanet:7.3.2", "geoplanet:7.4.0", "geoplanet:7.4.1", "geoplanet:7.5.1", "geoplanet:7.5.2", "geoplanet:7.6.0", "geoplanet:7.8.1", "geoplanet:7.9.0", "geoplanet:7.10.0", "geoplanet:8.0.0", "woeplanet:8.0.0"], "meta:indexed": "2020-08-20T20:15:32.987172", "meta:updated": "2020-10-14T11:44:06.883893", "woe:hierarchy": {"continent": 24865672, "country": 23424977, "town": 0, "planet": 1, "county": 12589530, "suburb": 0, "state": 2347594, "region": 0, "localadmin": 0}, "woe:timezone_id": 56043648, "woe:hash": "dpqtd0f7c5zf", "woe:centroid": [-80.768341, 41.752831], "geom:latitude": 41.752831, "geom:longitude": -80.768341, "geom:hash": "dpqtd0f7c5zf", "woe:latitude": 41.752831, "geom:centroid": [-80.768341, 41.752831], "woe:longitude": -80.768341, "woe:repo": "woeplanet-airport-us", "geom:area": 0.0, "woe:scale": 19}}