{"type": "Feature", "id": 23418442, "geometry": {"type": "Point", "coordinates": [-89.869667, 35.349178]}, "properties": {"woe:id": 23418442, "woe:parent_id": 2451508, "woe:name": "Millinton Municipal Airport", "woe:placetype": 14, "woe:placetype_name": "Airport", "woe:lang": "ENG", "iso:country": "US", "meta:provider": ["geoplanet:7.3.1", "geoplanet:7.3.2", "geoplanet:7.4.0", "geoplanet:7.4.1", "geoplanet:7.5.1", "geoplanet:7.5.2", "geoplanet:7.6.0", "geoplanet:7.8.1", "geoplanet:7.9.0", "geoplanet:7.10.0", "geoplanet:8.0.0", "woeplanet:8.0.0"], "meta:indexed": "2020-08-20T20:15:32.888386", "meta:updated": "2020-10-14T11:44:06.709840", "woe:alias_ENG_V": ["NQA", "Millington Rgnl Jetport", "Millington Regional Jetport"], "woe:hierarchy": {"continent": 24865672, "country": 23424977, "town": 0, "planet": 1, "county": 12589990, "suburb": 0, "state": 2347601, "region": 0, "localadmin": 0}, "woe:timezone_id": 56043661, "woe:hash": "dn214gnguurk", "woe:centroid": [-89.869667, 35.349178], "geom:latitude": 35.349178, "geom:longitude": -89.869667, "geom:hash": "dn214gnguurk", "woe:latitude": 35.349178, "geom:centroid": [-89.869667, 35.349178], "woe:longitude": -89.869667, "woe:repo": "woeplanet-airport-us", "geom:area": 0.0, "woe:scale": 19}}