{"type": "Feature", "id": 12519910, "geometry": {"type": "Point", "coordinates": [-106.60685, 48.221882]}, "properties": {"woe:id": 12519910, "woe:parent_id": 2410627, "woe:name": "Glasgow International Airport", "woe:placetype": 14, "woe:placetype_name": "Airport", "woe:lang": "ENG", "iso:country": "US", "meta:provider": ["geoplanet:7.3.1", "geoplanet:7.3.2", "geoplanet:7.4.0", "geoplanet:7.4.1", "geoplanet:7.5.1", "geoplanet:7.5.2", "geoplanet:7.6.0", "geoplanet:7.8.1", "geoplanet:7.9.0", "geoplanet:7.10.0", "geoplanet:8.0.0", "woeplanet:8.0.0"], "meta:indexed": "2020-08-20T20:15:33.912578", "woe:alias_ENG_V": ["Wokal Field-Glasgow Int'l Airport", "GGW Airport", "Glasgow Airport", "Wokel Field-Glasgow International Airport", "GGW", "Wokal Field - Glasgow Int'l Airport", "Wokal Field - Glasgow International Airport"], "meta:updated": "2020-10-14T11:44:08.245927", "woe:hierarchy": {"continent": 24865672, "country": 23424977, "town": 0, "planet": 1, "county": 12589133, "suburb": 0, "state": 2347585, "region": 0, "localadmin": 0}, "woe:timezone_id": 56043665, "woe:hash": "c8s4q4e2b674", "woe:centroid": [-106.60685, 48.221882], "geom:latitude": 48.221882, "geom:longitude": -106.60685, "geom:hash": "c8s4q4e2b674", "woe:latitude": 48.221882, "geom:centroid": [-106.60685, 48.221882], "woe:longitude": -106.60685, "woe:repo": "woeplanet-airport-us", "geom:area": 0.0, "woe:scale": 19}}