{"type": "Feature", "id": 29388450, "properties": {"woe:id": 29388450, "woe:parent_id": 2356929, "woe:name": "Blue Swan Airport", "woe:placetype": 14, "woe:placetype_name": "Airport", "woe:lang": "ENG", "iso:country": "US", "meta:provider": ["geoplanet:7.3.1", "geoplanet:7.3.2", "geoplanet:7.4.0", "geoplanet:7.4.1", "geoplanet:7.5.1", "geoplanet:7.5.2", "geoplanet:7.6.0", "geoplanet:7.8.1", "geoplanet:7.9.0", "geoplanet:7.10.0", "geoplanet:8.0.0", "woeplanet:8.0.0"], "meta:indexed": "2020-08-20T20:15:33.005325", "meta:updated": "2020-08-22T02:54:57.998995", "woe:hierarchy": {"continent": 24865672, "country": 23424977, "town": 0, "planet": 1, "county": 12589735, "suburb": 0, "state": 2347597, "region": 0, "localadmin": 0}, "woe:timezone_id": 56043648, "woe:hash": "dr3wcg4d99g5", "woe:centroid": [-76.560219, 41.984692], "geom:latitude": 41.984692, "geom:longitude": -76.560219, "geom:hash": "dr3wcg4d99g5", "woe:latitude": 41.984692, "geom:centroid": [-76.560219, 41.984692], "woe:longitude": -76.560219, "woe:repo": "woeplanet-airport-us"}, "geometry": {"coordinates": [-76.560219, 41.984692], "type": "Point"}}