{"type": "Feature", "id": 12521604, "geometry": {"type": "Point", "coordinates": [-85.802399, 42.930649]}, "properties": {"woe:id": 12521604, "woe:parent_id": 2428977, "woe:name": "Riverview Airport", "woe:placetype": 14, "woe:placetype_name": "Airport", "woe:lang": "ENG", "iso:country": "US", "meta:provider": ["geoplanet:7.3.1", "geoplanet:7.3.2", "geoplanet:7.4.0", "geoplanet:7.4.1", "geoplanet:7.5.1", "geoplanet:7.5.2", "geoplanet:7.6.0", "geoplanet:7.8.1", "geoplanet:7.9.0", "geoplanet:7.10.0", "geoplanet:8.0.0", "woeplanet:8.0.0"], "meta:indexed": "2020-08-20T20:15:34.817763", "woe:alias_ENG_V": ["08c"], "meta:updated": "2020-10-14T11:44:07.632667", "woe:hierarchy": {"continent": 24865672, "country": 23424977, "town": 0, "planet": 1, "county": 12588783, "suburb": 0, "state": 2347581, "region": 0, "localadmin": 0}, "woe:timezone_id": 56043658, "woe:hash": "dpdupx295jn0", "woe:centroid": [-85.802399, 42.930649], "geom:latitude": 42.930649, "geom:longitude": -85.802399, "geom:hash": "dpdupx295jn0", "woe:latitude": 42.930649, "geom:centroid": [-85.802399, 42.930649], "woe:longitude": -85.802399, "woe:repo": "woeplanet-airport-us", "geom:area": 0.0, "woe:scale": 19}}