{"type": "Feature", "id": 12521734, "geometry": {"type": "Point", "coordinates": [-123.141457, 47.241928]}, "properties": {"woe:id": 12521734, "woe:parent_id": 2492259, "woe:name": "Sanderson Field Airport", "woe:placetype": 14, "woe:placetype_name": "Airport", "woe:lang": "ENG", "iso:country": "US", "meta:provider": ["geoplanet:7.3.1", "geoplanet:7.3.2", "geoplanet:7.4.0", "geoplanet:7.4.1", "geoplanet:7.5.1", "geoplanet:7.5.2", "geoplanet:7.6.0", "geoplanet:7.8.1", "geoplanet:7.9.0", "geoplanet:7.10.0", "geoplanet:8.0.0", "woeplanet:8.0.0"], "meta:indexed": "2020-08-20T20:15:32.480173", "woe:alias_ENG_V": ["SHN Airport", "Sanderson Airport", "Sanderson Field", "SHN"], "meta:updated": "2020-10-14T11:44:08.407383", "woe:hierarchy": {"continent": 24865672, "country": 23424977, "town": 0, "planet": 1, "county": 12590462, "suburb": 0, "state": 2347606, "region": 0, "localadmin": 0}, "woe:timezone_id": 56043663, "woe:hash": "c22kvb5hhjdt", "woe:centroid": [-123.141457, 47.241928], "geom:latitude": 47.241928, "geom:longitude": -123.141457, "geom:hash": "c22kvb5hhjdt", "woe:latitude": 47.241928, "geom:centroid": [-123.141457, 47.241928], "woe:longitude": -123.141457, "woe:repo": "woeplanet-airport-us", "geom:area": 0.0, "woe:scale": 19}}