{"type": "Feature", "id": 12520220, "properties": {"woe:id": 12520220, "woe:parent_id": 2424039, "woe:name": "Hooker Municipal Airport", "woe:placetype": 14, "woe:placetype_name": "Airport", "woe:lang": "ENG", "iso:country": "US", "meta:provider": ["geoplanet:7.3.1", "geoplanet:7.3.2", "geoplanet:7.4.0", "geoplanet:7.4.1", "geoplanet:7.5.1", "geoplanet:7.5.2", "geoplanet:7.6.0", "geoplanet:7.8.1", "geoplanet:7.9.0", "geoplanet:7.10.0", "geoplanet:8.0.0", "woeplanet:8.0.0"], "meta:indexed": "2020-08-20T20:15:32.107168", "meta:updated": "2020-08-22T02:54:57.515760", "woe:alias_ENG_V": ["Hooker Muni Airport", "O45"], "woe:hierarchy": {"continent": 24865672, "country": 23424977, "town": 0, "planet": 1, "county": 12589684, "suburb": 0, "state": 2347595, "region": 0, "localadmin": 0}, "woe:timezone_id": 56043661, "woe:hash": "9y818t8fyzvw", "woe:centroid": [-101.2267, 36.856899], "geom:latitude": 36.856899, "geom:longitude": -101.2267, "geom:hash": "9y818t8fyzvw", "woe:latitude": 36.856899, "geom:centroid": [-101.2267, 36.856899], "woe:longitude": -101.2267, "woe:repo": "woeplanet-airport-us"}, "geometry": {"coordinates": [-101.2267, 36.856899], "type": "Point"}}