{"type": "Feature", "id": 12519264, "geometry": {"type": "Point", "coordinates": [-116.811523, 47.773441]}, "properties": {"woe:id": 12519264, "woe:parent_id": 2418989, "woe:name": "Coeur d'Alene Air Term Airport", "woe:placetype": 14, "woe:placetype_name": "Airport", "woe:lang": "ENG", "iso:country": "US", "meta:provider": ["geoplanet:7.3.1", "geoplanet:7.3.2", "geoplanet:7.4.0", "geoplanet:7.4.1", "geoplanet:7.5.1", "geoplanet:7.5.2", "geoplanet:7.6.0", "geoplanet:7.8.1", "geoplanet:7.9.0", "geoplanet:7.10.0", "geoplanet:8.0.0", "woeplanet:8.0.0"], "meta:indexed": "2020-08-20T20:15:33.551268", "woe:alias_ENG_V": ["COE Airport", "Coeur d'Alene Air Term", "Coeur d'Alene Airport", "Coeur d'Alene Term", "Coeur d'Alene Term Airport", "COE", "Coeur D'alene - Pappy Boyington Field"], "meta:updated": "2020-10-14T11:44:09.923205", "woe:hierarchy": {"continent": 24865672, "country": 23424977, "town": 0, "planet": 1, "county": 12588061, "suburb": 0, "state": 2347571, "region": 0, "localadmin": 0}, "woe:timezone_id": 56043663, "woe:hash": "c2kzvbukqnz7", "woe:centroid": [-116.811523, 47.773441], "geom:latitude": 47.773441, "geom:longitude": -116.811523, "geom:hash": "c2kzvbukqnz7", "woe:latitude": 47.773441, "geom:centroid": [-116.811523, 47.773441], "woe:longitude": -116.811523, "woe:repo": "woeplanet-airport-us", "geom:area": 0.0, "woe:scale": 19}}