{"type": "Feature", "id": 29388448, "properties": {"woe:id": 29388448, "woe:parent_id": 2381567, "woe:name": "Carbondale-Clifford Airport", "woe:placetype": 14, "woe:placetype_name": "Airport", "woe:lang": "ENG", "iso:country": "US", "meta:provider": ["geoplanet:7.3.1", "geoplanet:7.3.2", "geoplanet:7.4.0", "geoplanet:7.4.1", "geoplanet:7.5.1", "geoplanet:7.5.2", "geoplanet:7.6.0", "geoplanet:7.8.1", "geoplanet:7.9.0", "geoplanet:7.10.0", "geoplanet:8.0.0", "woeplanet:8.0.0"], "meta:indexed": "2020-08-20T20:15:35.866063", "woe:alias_ENG_V": ["9pa1"], "meta:updated": "2020-08-22T02:54:59.980394", "woe:hierarchy": {"continent": 24865672, "country": 23424977, "town": 0, "planet": 1, "county": 12589785, "suburb": 0, "state": 2347597, "region": 0, "localadmin": 0}, "woe:timezone_id": 56043648, "woe:hash": "dr6kbjypwgnh", "woe:centroid": [-75.5774, 41.649101], "geom:latitude": 41.649101, "geom:longitude": -75.5774, "geom:hash": "dr6kbjypwgnh", "woe:latitude": 41.649101, "geom:centroid": [-75.5774, 41.649101], "woe:longitude": -75.5774, "woe:repo": "woeplanet-airport-us"}, "geometry": {"coordinates": [-75.5774, 41.649101], "type": "Point"}}