{"type": "Feature", "id": 12521361, "properties": {"woe:id": 12521361, "woe:parent_id": 2471215, "woe:name": "Philadelphia Municipal Airport", "woe:placetype": 14, "woe:placetype_name": "Airport", "woe:lang": "ENG", "iso:country": "US", "meta:provider": ["geoplanet:7.3.1", "geoplanet:7.3.2", "geoplanet:7.4.0", "geoplanet:7.4.1", "geoplanet:7.5.1", "geoplanet:7.5.2", "geoplanet:7.6.0", "geoplanet:7.8.1", "geoplanet:7.9.0", "geoplanet:7.10.0", "geoplanet:8.0.0", "woeplanet:8.0.0"], "meta:indexed": "2020-08-20T20:15:34.697011", "woe:alias_ENG_V": ["MPE Airport", "MPE", "Philadelphia Muni Airport"], "meta:updated": "2020-08-22T02:54:59.233966", "woe:hierarchy": {"continent": 24865672, "country": 23424977, "town": 0, "planet": 1, "county": 12588933, "suburb": 0, "state": 2347583, "region": 0, "localadmin": 0}, "woe:timezone_id": 56043661, "woe:hash": "djbdegq1npcm", "woe:centroid": [-89.123581, 32.80127], "geom:latitude": 32.80127, "geom:longitude": -89.123581, "geom:hash": "djbdegq1npcm", "woe:latitude": 32.80127, "geom:centroid": [-89.123581, 32.80127], "woe:longitude": -89.123581, "woe:repo": "woeplanet-airport-us"}, "geometry": {"coordinates": [-89.123581, 32.80127], "type": "Point"}}