{"type": "Feature", "id": 12519266, "geometry": {"type": "Point", "coordinates": [-95.582916, 37.104401]}, "properties": {"woe:id": 12519266, "woe:parent_id": 2357773, "woe:name": "Coffeyville Municipal Airport", "woe:placetype": 14, "woe:placetype_name": "Airport", "woe:lang": "ENG", "iso:country": "US", "meta:provider": ["geoplanet:7.3.1", "geoplanet:7.3.2", "geoplanet:7.4.0", "geoplanet:7.4.1", "geoplanet:7.5.1", "geoplanet:7.5.2", "geoplanet:7.6.0", "geoplanet:7.8.1", "geoplanet:7.9.0", "geoplanet:7.10.0", "geoplanet:8.0.0", "woeplanet:8.0.0"], "meta:indexed": "2020-08-20T20:15:33.552213", "woe:alias_ENG_V": ["Coffeyville Municipal", "CFV", "CFV Airport", "Coffeyville Airport", "Coffeyville Muni Airport"], "meta:updated": "2020-10-14T11:44:09.953571", "woe:hierarchy": {"continent": 24865672, "country": 23424977, "town": 0, "planet": 1, "county": 12588433, "suburb": 0, "state": 2347575, "region": 0, "localadmin": 0}, "woe:timezone_id": 56043661, "woe:hash": "9ys50fwsu9sj", "woe:centroid": [-95.582916, 37.104401], "geom:latitude": 37.104401, "geom:longitude": -95.582916, "geom:hash": "9ys50fwsu9sj", "woe:latitude": 37.104401, "geom:centroid": [-95.582916, 37.104401], "woe:longitude": -95.582916, "woe:repo": "woeplanet-airport-us", "geom:area": 0.0, "woe:scale": 19}}