{"type": "Feature", "id": 29387901, "geometry": {"type": "Point", "coordinates": [-105.298431, 31.25922]}, "properties": {"woe:id": 29387901, "woe:parent_id": 2450901, "woe:name": "Mile High Community Airport", "woe:placetype": 14, "woe:placetype_name": "Airport", "woe:lang": "ENG", "iso:country": "US", "meta:provider": ["geoplanet:7.3.1", "geoplanet:7.3.2", "geoplanet:7.4.0", "geoplanet:7.4.1", "geoplanet:7.5.1", "geoplanet:7.5.2", "geoplanet:7.6.0", "geoplanet:7.8.1", "geoplanet:7.9.0", "geoplanet:7.10.0", "geoplanet:8.0.0", "woeplanet:8.0.0"], "meta:indexed": "2020-08-20T20:15:35.438992", "meta:updated": "2020-10-14T11:44:06.752696", "woe:hierarchy": {"continent": 24865672, "country": 23424977, "town": 0, "planet": 1, "county": 12590121, "suburb": 0, "state": 2347602, "region": 0, "localadmin": 0}, "woe:timezone_id": 56043665, "woe:hash": "9tt1gfs40szn", "woe:centroid": [-105.298431, 31.25922], "geom:latitude": 31.25922, "geom:longitude": -105.298431, "geom:hash": "9tt1gfs40szn", "woe:latitude": 31.25922, "geom:centroid": [-105.298431, 31.25922], "woe:longitude": -105.298431, "woe:repo": "woeplanet-airport-us", "geom:area": 0.0, "woe:scale": 19}}