{"type": "Feature", "id": 12520201, "geometry": {"type": "Point", "coordinates": [-86.893898, 30.424999]}, "properties": {"woe:id": 12520201, "woe:parent_id": 2417845, "woe:name": "Holley Outlying Landing Field", "woe:placetype": 14, "woe:placetype_name": "Airport", "woe:lang": "ENG", "iso:country": "US", "meta:provider": ["geoplanet:7.3.1", "geoplanet:7.3.2", "geoplanet:7.4.0", "geoplanet:7.4.1", "geoplanet:7.5.1", "geoplanet:7.5.2", "geoplanet:7.6.0", "geoplanet:7.8.1", "geoplanet:7.9.0", "geoplanet:7.10.0", "geoplanet:8.0.0", "woeplanet:8.0.0"], "meta:indexed": "2020-08-20T20:15:32.103421", "meta:updated": "2020-10-14T11:44:08.138681", "woe:hierarchy": {"continent": 24865672, "country": 23424977, "town": 0, "planet": 1, "county": 12587857, "suburb": 0, "state": 2347568, "region": 0, "localadmin": 0}, "woe:timezone_id": 56043661, "woe:hash": "dj6jndty3qvs", "woe:centroid": [-86.893898, 30.424999], "geom:latitude": 30.424999, "geom:longitude": -86.893898, "geom:hash": "dj6jndty3qvs", "woe:latitude": 30.424999, "geom:centroid": [-86.893898, 30.424999], "woe:longitude": -86.893898, "woe:repo": "woeplanet-airport-us", "geom:area": 0.0, "woe:scale": 19}}