{"type": "Feature", "id": 12522443, "properties": {"woe:id": 12522443, "woe:parent_id": 2419118, "woe:name": "Wilkes County Airport", "woe:placetype": 14, "woe:placetype_name": "Airport", "woe:lang": "ENG", "iso:country": "US", "meta:provider": ["geoplanet:7.3.1", "geoplanet:7.3.2", "geoplanet:7.4.0", "geoplanet:7.4.1", "geoplanet:7.5.1", "geoplanet:7.5.2", "geoplanet:7.6.0", "geoplanet:7.8.1", "geoplanet:7.9.0", "geoplanet:7.10.0", "geoplanet:8.0.0", "woeplanet:8.0.0"], "meta:indexed": "2020-08-20T20:15:35.227505", "woe:alias_ENG_V": ["UKF Airport", "UKF"], "meta:updated": "2020-08-22T02:54:58.183801", "woe:hierarchy": {"continent": 24865672, "country": 23424977, "town": 0, "planet": 1, "county": 12589470, "suburb": 0, "state": 2347592, "region": 0, "localadmin": 0}, "woe:timezone_id": 56043648, "woe:hash": "dnqq4e0361hw", "woe:centroid": [-81.100639, 36.227638], "geom:latitude": 36.227638, "geom:longitude": -81.100639, "geom:hash": "dnqq4e0361hw", "woe:latitude": 36.227638, "geom:centroid": [-81.100639, 36.227638], "woe:longitude": -81.100639, "woe:repo": "woeplanet-airport-us"}, "geometry": {"coordinates": [-81.100639, 36.227638], "type": "Point"}}