{"type": "Feature", "id": 29388018, "properties": {"woe:id": 29388018, "woe:parent_id": 2405279, "woe:name": "Forest Lake Airport", "woe:placetype": 14, "woe:placetype_name": "Airport", "woe:lang": "ENG", "iso:country": "US", "meta:provider": ["geoplanet:7.3.1", "geoplanet:7.3.2", "geoplanet:7.4.0", "geoplanet:7.4.1", "geoplanet:7.5.1", "geoplanet:7.5.2", "geoplanet:7.6.0", "geoplanet:7.8.1", "geoplanet:7.9.0", "geoplanet:7.10.0", "geoplanet:8.0.0", "woeplanet:8.0.0"], "meta:indexed": "2020-08-20T20:15:35.569247", "woe:alias_ENG_V": ["25d"], "meta:updated": "2020-08-22T02:54:59.838699", "woe:hierarchy": {"continent": 24865672, "country": 23424977, "town": 0, "planet": 1, "county": 12588878, "suburb": 0, "state": 2347582, "region": 0, "localadmin": 0}, "woe:timezone_id": 56043661, "woe:hash": "cbjc7y1mmhhu", "woe:centroid": [-92.99733, 45.253609], "geom:latitude": 45.253609, "geom:longitude": -92.99733, "geom:hash": "cbjc7y1mmhhu", "woe:latitude": 45.253609, "geom:centroid": [-92.99733, 45.253609], "woe:longitude": -92.99733, "woe:repo": "woeplanet-airport-us"}, "geometry": {"coordinates": [-92.99733, 45.253609], "type": "Point"}}