{"type": "Feature", "id": 12523389, "properties": {"woe:id": 12523389, "woe:parent_id": 2454876, "woe:name": "Detroit Naval Air Facility", "woe:placetype": 14, "woe:placetype_name": "Airport", "woe:lang": "ENG", "iso:country": "US", "meta:provider": ["geoplanet:7.3.1", "geoplanet:7.3.2", "geoplanet:7.4.0", "geoplanet:7.4.1", "geoplanet:7.5.1", "geoplanet:7.5.2", "geoplanet:7.6.0", "geoplanet:7.8.1", "geoplanet:7.9.0", "geoplanet:7.10.0", "geoplanet:8.0.0", "woeplanet:8.0.0"], "meta:indexed": "2020-08-20T20:15:32.751253", "woe:alias_ENG_V": ["NFB Airport", "NFB"], "meta:updated": "2020-08-22T02:54:57.871222", "woe:hierarchy": {"continent": 24865672, "country": 23424977, "town": 0, "planet": 1, "county": 12588763, "suburb": 0, "state": 2347581, "region": 0, "localadmin": 0}, "woe:timezone_id": 56043658, "woe:hash": "dpt4655tcbbe", "woe:centroid": [-82.875977, 42.600479], "geom:latitude": 42.600479, "geom:longitude": -82.875977, "geom:hash": "dpt4655tcbbe", "woe:latitude": 42.600479, "geom:centroid": [-82.875977, 42.600479], "woe:longitude": -82.875977, "woe:repo": "woeplanet-airport-us"}, "geometry": {"coordinates": [-82.875977, 42.600479], "type": "Point"}}