{"type": "Feature", "id": 12520557, "geometry": {"type": "Point", "coordinates": [-156.950256, 20.79055]}, "properties": {"woe:id": 12520557, "woe:parent_id": 2430856, "woe:name": "Lanai Airport", "woe:placetype": 14, "woe:placetype_name": "Airport", "woe:lang": "ENG", "iso:country": "US", "meta:provider": ["geoplanet:7.3.1", "geoplanet:7.3.2", "geoplanet:7.4.0", "geoplanet:7.4.1", "geoplanet:7.5.1", "geoplanet:7.5.2", "geoplanet:7.6.0", "geoplanet:7.8.1", "geoplanet:7.9.0", "geoplanet:7.10.0", "geoplanet:8.0.0", "woeplanet:8.0.0"], "meta:indexed": "2020-08-20T20:15:34.257599", "woe:alias_ENG_V": ["LNY Airport", "LNY"], "meta:updated": "2020-10-14T11:44:09.696480", "woe:hierarchy": {"continent": 24865672, "country": 23424977, "town": 0, "planet": 1, "county": 12588033, "suburb": 0, "state": 2347570, "region": 0, "localadmin": 0}, "woe:timezone_id": 28350949, "woe:hash": "8e8qk8b39zqv", "woe:centroid": [-156.950256, 20.79055], "geom:latitude": 20.79055, "geom:longitude": -156.950256, "geom:hash": "8e8qk8b39zqv", "woe:latitude": 20.79055, "geom:centroid": [-156.950256, 20.79055], "woe:longitude": -156.950256, "woe:repo": "woeplanet-airport-us", "geom:area": 0.0, "woe:scale": 19}}