{"type": "Feature", "id": 12520946, "properties": {"woe:id": 12520946, "woe:parent_id": 2379551, "woe:name": "Mignon Laird Municipal Airport", "woe:placetype": 14, "woe:placetype_name": "Airport", "woe:lang": "ENG", "iso:country": "US", "meta:provider": ["geoplanet:7.3.1", "geoplanet:7.3.2", "geoplanet:7.4.0", "geoplanet:7.4.1", "geoplanet:7.5.1", "geoplanet:7.5.2", "geoplanet:7.6.0", "geoplanet:7.8.1", "geoplanet:7.9.0", "geoplanet:7.10.0", "geoplanet:8.0.0", "woeplanet:8.0.0"], "meta:indexed": "2020-08-20T20:15:34.464168", "woe:alias_ENG_V": ["93f", "Mignon Laird Muni Airport"], "meta:updated": "2020-08-22T02:54:59.120833", "woe:hierarchy": {"continent": 24865672, "country": 23424977, "town": 0, "planet": 1, "county": 12589679, "suburb": 0, "state": 2347595, "region": 0, "localadmin": 0}, "woe:timezone_id": 56043661, "woe:hash": "9y34e4x4urbr", "woe:centroid": [-99.702118, 35.609951], "geom:latitude": 35.609951, "geom:longitude": -99.702118, "geom:hash": "9y34e4x4urbr", "woe:latitude": 35.609951, "geom:centroid": [-99.702118, 35.609951], "woe:longitude": -99.702118, "woe:repo": "woeplanet-airport-us"}, "geometry": {"coordinates": [-99.702118, 35.609951], "type": "Point"}}