{"type": "Feature", "id": 12520723, "geometry": {"type": "Point", "coordinates": [-112.358589, 33.540081]}, "properties": {"woe:id": 12520723, "woe:parent_id": 2515783, "woe:name": "Luke Air Force Base", "woe:placetype": 14, "woe:placetype_name": "Airport", "woe:lang": "ENG", "iso:country": "US", "meta:provider": ["geoplanet:7.3.1", "geoplanet:7.3.2", "geoplanet:7.4.0", "geoplanet:7.4.1", "geoplanet:7.5.1", "geoplanet:7.5.2", "geoplanet:7.6.0", "geoplanet:7.8.1", "geoplanet:7.9.0", "geoplanet:7.10.0", "geoplanet:8.0.0", "woeplanet:8.0.0"], "meta:indexed": "2020-08-20T20:15:32.239893", "woe:alias_ENG_V": ["Luke AFB", "Luke Air Base", "Luke Base", "LUF", "LUF Airport", "Glendale Luke Base"], "meta:updated": "2020-10-14T11:44:07.869638", "woe:hierarchy": {"continent": 24865672, "country": 23424977, "town": 0, "planet": 1, "county": 12587587, "suburb": 0, "state": 2347561, "region": 0, "localadmin": 0}, "woe:timezone_id": 56043666, "woe:hash": "9tbng1ycph78", "woe:centroid": [-112.358589, 33.540081], "geom:latitude": 33.540081, "geom:longitude": -112.358589, "geom:hash": "9tbng1ycph78", "woe:latitude": 33.540081, "geom:centroid": [-112.358589, 33.540081], "woe:longitude": -112.358589, "woe:repo": "woeplanet-airport-us", "geom:area": 0.0, "woe:scale": 19}}