{"type": "Feature", "id": 12519418, "geometry": {"type": "Point", "coordinates": [-90.57943, 41.613682]}, "properties": {"woe:id": 12519418, "woe:parent_id": 2389559, "woe:name": "Davenport Municipal Airport", "woe:placetype": 14, "woe:placetype_name": "Airport", "woe:lang": "ENG", "iso:country": "US", "meta:provider": ["geoplanet:7.3.1", "geoplanet:7.3.2", "geoplanet:7.4.0", "geoplanet:7.4.1", "geoplanet:7.5.1", "geoplanet:7.5.2", "geoplanet:7.6.0", "geoplanet:7.8.1", "geoplanet:7.9.0", "geoplanet:7.10.0", "geoplanet:8.0.0", "woeplanet:8.0.0"], "meta:indexed": "2020-08-20T20:15:33.648742", "woe:alias_ENG_V": ["DVN Airport", "Davenport Airport", "Davenport Municipal", "DVN", "Davenport Muni Airport"], "meta:updated": "2020-10-14T11:44:08.592821", "woe:hierarchy": {"continent": 24865672, "country": 23424977, "town": 0, "planet": 1, "county": 12588353, "suburb": 0, "state": 2347574, "region": 0, "localadmin": 0}, "woe:timezone_id": 56043661, "woe:hash": "9zrsdzd1629d", "woe:centroid": [-90.57943, 41.613682], "geom:latitude": 41.613682, "geom:longitude": -90.57943, "geom:hash": "9zrsdzd1629d", "woe:latitude": 41.613682, "geom:centroid": [-90.57943, 41.613682], "woe:longitude": -90.57943, "woe:repo": "woeplanet-airport-us", "geom:area": 0.0, "woe:scale": 19}}