{"type": "Feature", "id": 12520048, "geometry": {"type": "Point", "coordinates": [-83.965881, 33.982491]}, "properties": {"woe:id": 12520048, "woe:parent_id": 2437315, "woe:name": "Gwinnett County Airport-Briscoe Field", "woe:placetype": 14, "woe:placetype_name": "Airport", "woe:lang": "ENG", "iso:country": "US", "meta:provider": ["geoplanet:7.3.1", "geoplanet:7.3.2", "geoplanet:7.4.0", "geoplanet:7.4.1", "geoplanet:7.5.1", "geoplanet:7.5.2", "geoplanet:7.6.0", "geoplanet:7.8.1", "geoplanet:7.9.0", "geoplanet:7.10.0", "geoplanet:8.0.0", "woeplanet:8.0.0"], "meta:indexed": "2020-08-20T20:15:33.984043", "woe:alias_ENG_V": ["Gwinnett Cnty Airport-Briscoe Field", "LZU Airport", "LZU", "Gwinnett County - Briscoe Field"], "meta:updated": "2020-10-14T11:44:09.617362", "woe:hierarchy": {"continent": 24865672, "country": 23424977, "town": 0, "planet": 1, "county": 12587936, "suburb": 0, "state": 2347569, "region": 0, "localadmin": 0}, "woe:timezone_id": 56043648, "woe:hash": "dnh3363fm5mn", "woe:centroid": [-83.965881, 33.982491], "geom:latitude": 33.982491, "geom:longitude": -83.965881, "geom:hash": "dnh3363fm5mn", "woe:latitude": 33.982491, "geom:centroid": [-83.965881, 33.982491], "woe:longitude": -83.965881, "woe:repo": "woeplanet-airport-us", "geom:area": 0.0, "woe:scale": 19}}