{"type": "Feature", "id": 12521446, "geometry": {"type": "Point", "coordinates": [-81.248627, 41.208649]}, "properties": {"woe:id": 12521446, "woe:parent_id": 2478864, "woe:name": "Portage County Airport", "woe:placetype": 14, "woe:placetype_name": "Airport", "woe:lang": "ENG", "iso:country": "US", "meta:provider": ["geoplanet:7.3.1", "geoplanet:7.3.2", "geoplanet:7.4.0", "geoplanet:7.4.1", "geoplanet:7.5.1", "geoplanet:7.5.2", "geoplanet:7.6.0", "geoplanet:7.8.1", "geoplanet:7.9.0", "geoplanet:7.10.0", "geoplanet:8.0.0", "woeplanet:8.0.0"], "meta:indexed": "2020-08-20T20:15:34.737007", "woe:alias_ENG_V": ["28g", "29G"], "meta:updated": "2020-10-14T11:44:09.299302", "woe:hierarchy": {"continent": 24865672, "country": 23424977, "town": 0, "planet": 1, "county": 12589593, "suburb": 0, "state": 2347594, "region": 0, "localadmin": 0}, "woe:timezone_id": 56043648, "woe:hash": "dpq4rju9cbbw", "woe:centroid": [-81.248627, 41.208649], "geom:latitude": 41.208649, "geom:longitude": -81.248627, "geom:hash": "dpq4rju9cbbw", "woe:latitude": 41.208649, "geom:centroid": [-81.248627, 41.208649], "woe:longitude": -81.248627, "woe:repo": "woeplanet-airport-us", "geom:area": 0.0, "woe:scale": 19}}