{"type": "Feature", "id": 12520253, "geometry": {"type": "Point", "coordinates": [-87.304703, 39.460159]}, "properties": {"woe:id": 12520253, "woe:parent_id": 2504883, "woe:name": "Terre Haute International Airport", "woe:placetype": 14, "woe:placetype_name": "Airport", "woe:lang": "ENG", "iso:country": "US", "meta:provider": ["geoplanet:7.3.1", "geoplanet:7.3.2", "geoplanet:7.4.0", "geoplanet:7.4.1", "geoplanet:7.5.1", "geoplanet:7.5.2", "geoplanet:7.6.0", "geoplanet:7.8.1", "geoplanet:7.9.0", "geoplanet:7.10.0", "geoplanet:8.0.0", "woeplanet:8.0.0"], "meta:indexed": "2020-08-20T20:15:34.099022", "woe:alias_ENG_V": ["Terre Haute Int'l Airport", "Hulman Regional", "HUF", "Terre Haute International", "Hulman Regional Airport", "HUF Airport", "Hulman Airport", "Terre Haute Int'l-hulman Field", "Terre Haute International-hulman Field"], "meta:updated": "2020-10-14T11:44:08.107652", "woe:hierarchy": {"continent": 24865672, "country": 23424977, "town": 0, "planet": 1, "county": 12588263, "suburb": 0, "state": 2347573, "region": 0, "localadmin": 0}, "woe:timezone_id": 56043656, "woe:hash": "dp1bmrd8hfz1", "woe:centroid": [-87.304703, 39.460159], "geom:latitude": 39.460159, "geom:longitude": -87.304703, "geom:hash": "dp1bmrd8hfz1", "woe:latitude": 39.460159, "geom:centroid": [-87.304703, 39.460159], "woe:longitude": -87.304703, "woe:repo": "woeplanet-airport-us", "geom:area": 0.0, "woe:scale": 19}}