{"type": "Feature", "id": 12520060, "properties": {"woe:id": 12520060, "woe:parent_id": 2416363, "woe:name": "Hallock Municipal Airport", "woe:placetype": 14, "woe:placetype_name": "Airport", "woe:lang": "ENG", "iso:country": "US", "meta:provider": ["geoplanet:7.3.1", "geoplanet:7.3.2", "geoplanet:7.4.0", "geoplanet:7.4.1", "geoplanet:7.5.1", "geoplanet:7.5.2", "geoplanet:7.6.0", "geoplanet:7.8.1", "geoplanet:7.9.0", "geoplanet:7.10.0", "geoplanet:8.0.0", "woeplanet:8.0.0"], "meta:indexed": "2020-08-20T20:15:33.990811", "woe:alias_ENG_V": ["HCO Airport", "HCO", "Hallock Muni Airport"], "meta:updated": "2020-08-22T02:54:58.898482", "woe:hierarchy": {"continent": 24865672, "country": 23424977, "town": 0, "planet": 1, "county": 12588831, "suburb": 0, "state": 2347582, "region": 0, "localadmin": 0}, "woe:timezone_id": 56043661, "woe:hash": "cbej65k8j0tj", "woe:centroid": [-96.936958, 48.753208], "geom:latitude": 48.753208, "geom:longitude": -96.936958, "geom:hash": "cbej65k8j0tj", "woe:latitude": 48.753208, "geom:centroid": [-96.936958, 48.753208], "woe:longitude": -96.936958, "woe:repo": "woeplanet-airport-us"}, "geometry": {"coordinates": [-96.936958, 48.753208], "type": "Point"}}