{"type": "Feature", "id": 12518650, "geometry": {"type": "Point", "coordinates": [-98.620338, 33.585899]}, "properties": {"woe:id": 12518650, "woe:parent_id": 2355592, "woe:name": "Archer City Municipal Airport", "woe:placetype": 14, "woe:placetype_name": "Airport", "woe:lang": "ENG", "iso:country": "US", "meta:provider": ["geoplanet:7.3.1", "geoplanet:7.3.2", "geoplanet:7.4.0", "geoplanet:7.4.1", "geoplanet:7.5.1", "geoplanet:7.5.2", "geoplanet:7.6.0", "geoplanet:7.8.1", "geoplanet:7.9.0", "geoplanet:7.10.0", "geoplanet:8.0.0", "woeplanet:8.0.0"], "meta:indexed": "2020-08-20T20:15:33.157775", "woe:alias_ENG_V": ["T39"], "meta:updated": "2020-10-14T11:44:08.691401", "woe:hierarchy": {"continent": 24865672, "country": 23424977, "town": 0, "planet": 1, "county": 12590011, "suburb": 0, "state": 2347602, "region": 0, "localadmin": 0}, "woe:timezone_id": 56043661, "woe:hash": "9vcz5f4u5965", "woe:centroid": [-98.620338, 33.585899], "geom:latitude": 33.585899, "geom:longitude": -98.620338, "geom:hash": "9vcz5f4u5965", "woe:latitude": 33.585899, "geom:centroid": [-98.620338, 33.585899], "woe:longitude": -98.620338, "woe:repo": "woeplanet-airport-us", "geom:area": 0.0, "woe:scale": 19}}