{"type": "Feature", "id": 12520003, "properties": {"woe:id": 12520003, "woe:parent_id": 2414587, "woe:name": "Greenville Airport", "woe:placetype": 14, "woe:placetype_name": "Airport", "woe:lang": "ENG", "iso:country": "US", "meta:provider": ["geoplanet:7.3.1", "geoplanet:7.3.2", "geoplanet:7.4.0", "geoplanet:7.4.1", "geoplanet:7.5.1", "geoplanet:7.5.2", "geoplanet:7.6.0", "geoplanet:7.8.1", "geoplanet:7.9.0", "geoplanet:7.10.0", "geoplanet:8.0.0", "woeplanet:8.0.0"], "meta:indexed": "2020-08-20T20:15:33.958555", "woe:alias_ENG_V": ["GRE Airport", "GRE"], "meta:updated": "2020-08-22T02:54:58.086401", "woe:hierarchy": {"continent": 24865672, "country": 23424977, "town": 0, "planet": 1, "county": 12588080, "suburb": 0, "state": 2347572, "region": 0, "localadmin": 0}, "woe:timezone_id": 56043661, "woe:hash": "dnbkym9g5s4p", "woe:centroid": [-89.371223, 38.834461], "geom:latitude": 38.834461, "geom:longitude": -89.371223, "geom:hash": "dnbkym9g5s4p", "woe:latitude": 38.834461, "geom:centroid": [-89.371223, 38.834461], "woe:longitude": -89.371223, "woe:repo": "woeplanet-airport-us"}, "geometry": {"coordinates": [-89.371223, 38.834461], "type": "Point"}}