{"type": "Feature", "id": 12522509, "geometry": {"type": "Point", "coordinates": [-119.1064, 36.398899]}, "properties": {"woe:id": 12522509, "woe:parent_id": 2523141, "woe:name": "Woodlake Airport", "woe:placetype": 14, "woe:placetype_name": "Airport", "woe:lang": "ENG", "iso:country": "US", "meta:provider": ["geoplanet:7.3.1", "geoplanet:7.3.2", "geoplanet:7.4.0", "geoplanet:7.4.1", "geoplanet:7.5.1", "geoplanet:7.5.2", "geoplanet:7.6.0", "geoplanet:7.8.1", "geoplanet:7.9.0", "geoplanet:7.10.0", "geoplanet:8.0.0", "woeplanet:8.0.0"], "meta:indexed": "2020-08-20T20:15:32.686737", "meta:updated": "2020-10-14T11:44:07.755467", "woe:alias_ENG_V": ["O42"], "woe:hierarchy": {"continent": 24865672, "country": 23424977, "town": 0, "planet": 1, "county": 12587723, "suburb": 0, "state": 2347563, "region": 0, "localadmin": 0}, "woe:timezone_id": 56043663, "woe:hash": "9q7r1djqgwx4", "woe:centroid": [-119.1064, 36.398899], "geom:latitude": 36.398899, "geom:longitude": -119.1064, "geom:hash": "9q7r1djqgwx4", "woe:latitude": 36.398899, "geom:centroid": [-119.1064, 36.398899], "woe:longitude": -119.1064, "woe:repo": "woeplanet-airport-us", "geom:area": 0.0, "woe:scale": 19}}